Workbook

Sheet backlog
C1: jour | I1: 1 | J1: 2 | K1: 3 | L1: 4 | M1: 5 | N1: 6 | O1: 7 | P1: 8 | Q1: 9 | R1: 10 | S1: 11 | T1: 12 | U1: 13 | V1: 14 | W1: 15 | X1: 16 | Y1: 17 | Z1: 18 | AA1: 19 | AB1: 20 | AC1: 21
C2: Sommaire effort restant | I2: =J10 -> 549 | J2: =L10 -> 539 | K2: =N10 -> 536 | L2: =P10 -> 532 | M2: =R10 -> 532 | N2: =T10 -> 518 | O2: =V10 -> 503 | P2: =X10 -> 498 | Q2: =Z10 -> 484 | R2: =AB10 -> 473 | S2: =AD10 -> 458 | T2: =AF10 -> 448 | U2: =AH10 -> 421 | V2: =AJ10 -> 391 | W2: =AL10 -> 366 | X2: =AN10 -> 344 | Y2: =AP10 -> 344 | Z2: =AR10 -> 337 | AA2: =AT10 -> 328 | AB2: =AV10 -> 319 | AC2: =AX10 -> 283 | AD2: =AZ10 -> 271
C3: Sommaire efforts dépensé | I3: =K10 -> 9 | J3: =M10 -> 6 | K3: =O10 -> 4 | L3: =Q10 -> 4 | M3: =S10 -> 15 | N3: =U10 -> 15 | O3: =W10 -> 17 | P3: =Y10 -> 22 | Q3: =AA10 -> 18 | R3: =AC10 -> 14 | S3: =AE10 -> 16 | T3: =AG10 -> 34 | U3: =AI10 -> 29 | V3: =AK10 -> 27 | W3: =AM10 -> 23 | X3: =AO10 -> 12 | Y3: =AQ10 -> 11 | Z3: =AS10 -> 13 | AA3: =AU10 -> 19 | AB3: =AW10 -> 34 | AC3: =AY10 -> 0 | AD3: =BA10 -> 0 | AH3: =SUM(I3:AD3) -> 342
C6: Sprint 1 : Mettre en place les fonctionnalités de base pour l’authentification, la gestion du profil, des cours, des échéances, du calendrier et des notifications d’un système académique et financier.
X7: 45971 | Z7: 45972 | AB7: 45973 | AD7: 45974 | AF7: 45975 | AH7: 45976 | AJ7: 45977 | AL7: 45978 | AN7: 45979 | AP7: 45980 | AR7: 45981 | AT7: 45982 | AV7: 45983 | AX7: 45984
B8: Numéro item product backlog | D8: Équipe | I8: jours du sprint / (effort restant estimé en début de journée | heures travaillées ce jour) | BB8: Total pour tâche | BC8: Total pour tâche par membre équipe
C9: Cas d'utilisation ou user-story/tâche | I9: 0 | J9: =I9+1 -> 1 | L9: =J9+1 -> 2 | N9: =L9+1 -> 3 | P9: =N9+1 -> 4 | R9: =P9+1 -> 5 | T9: =R9+1 -> 6 | V9: =T9+1 -> 7 | X9: =V9+1 -> 8 | Z9: =X9+1 -> 9 | AB9: =Z9+1 -> 10 | AD9: =AB9+1 -> 11 | AF9: =AD9+1 -> 12 | AH9: =AF9+1 -> 13 | AJ9: =AH9+1 -> 14 | AL9: =AJ9+1 -> 15 | AN9: =AL9+1 -> 16 | AP9: =AN9+1 -> 17 | AR9: =AP9+1 -> 18 | AT9: =AR9+1 -> 19 | AV9: =AT9+1 -> 20 | AX9: 21 | AZ9: =AX9+1 -> 22 | BC9: =D10 -> Oryna | BD9: =F10 -> Romuald | BE9: =G10 -> Kenny | BF9: =E10 -> Aziz | BG9: =H10 -> Joana
D10: =team!D2 -> Oryna | E10: =team!D3 -> Aziz | F10: =team!D6 -> Romuald | G10: =team!D5 -> Kenny | H10: =team!D4 -> Joana | I10: =SUM(I11:I506) -> 555 | J10: =SUM(J11:J506) -> 549 | K10: =SUM(K11:K506) -> 9 | L10: =SUM(L11:L506) -> 539 | M10: =SUM(M11:M506) -> 6 | N10: =SUM(N11:N506) -> 536 | O10: =SUM(O11:O506) -> 4 | P10: =SUM(P11:P506) -> 532 | ... AX10: =SUM(AX11:AX506) -> 283 | AZ10: =SUM(AZ11:AZ506) -> 271 | BB10: =SUM(BB11:BB506) -> 366 | BC10: =SUM(BC11:BC506) -> 88 | BD10: =SUM(BD11:BD506) -> 69 | BE10: =SUM(BE11:BE506) -> 41 | BF10: =SUM(BF11:BF506) -> 77 | BG10: =SUM(BG11:BG506) -> 72
A11: SPRINT 1 | B11: 1 | C11: Authentification utilisateur | D11: 1
C12: Création de la page de connexion | D12: 1 | E12: 0 | F12: 0 | G12: 0 | H12: 0 | I12: 8 | J12: =I12 -> 8 | K12: 2 | L12: =J12-K12 -> 6 | M12: 1 | N12: =L12-M12 -> 5 | O12: 0 | P12: =N12-O12 -> 5 | Q12: 0 | R12: =P12-Q12 -> 5 | S12: 1 | T12: =R12-S12 -> 4 | U12: 0 | V12: =T12-U12 -> 4 | W12: 0 | X12: =V12-W12 -> 4 | Y12: 1 | Z12: =X12-Y12 -> 3 | AA12: 0 | AB12: =Z12-AA12 -> 3 | AC12: 1 | AD12: =AB12-AC12 -> 2 | AE12: 1 | AF12: =AD12-AE12 -> 1 | AG12: 0 | AH12: =AF12-AG12 -> 1 | AI12: 1 | AJ12: =AH12-AI12 -> 0 | AK12: 0 | AL12: =AJ12-AK12 -> 0 | AM12: 0 | AN12: =AL12-AM12 -> 0 | AO12: 0 | AP12: =AN12-AO12 -> 0 | AQ12: 0 | AR12: =AP12-AQ12 -> 0 | AS12: 0 | AT12: =AR12-AS12 -> 0 | AU12: 0 | AV12: =AT12-AU12 -> 0 | AW12: 0 | AX12: =AV12-AW12 -> 0 | AY12: 0 | AZ12: =AX12-AY12 -> 0 | BB12: =AY12+AW12+AU12+AS12+AQ12+AO12+AM12+AK12+AI12+AG12+AE12+AC12+AA12+Y12+W12+U12+S12+Q12+O12+M12+K12 -> 8 | BC12: =BB12*D12 -> 8 | BD12: =BC12*F12 -> 0 | BE12: =BD12*G12 -> 0 | BF12: =BB12*E12 -> 0 | BG12: =BB12*H12 -> 0
C13: Creation de la page d'inscription | D13: 1 | E13: 0 | F13: 0 | G13: 0 | H13: =1-D13-E13 -> 0 | I13: 8 | J13: =I13 -> 8 | K13: 0 | L13: =J13-K13 -> 8 | M13: 0 | N13: =L13-M13 -> 8 | O13: 0 | P13: =N13-O13 -> 8 | Q13: 0 | R13: =P13-Q13 -> 8 | S13: 0 | T13: =R13-S13 -> 8 | U13: 0 | V13: =T13-U13 -> 8 | W13: 0 | X13: =V13-W13 -> 8 | Y13: 0 | Z13: =X13-Y13 -> 8 | AA13: 0 | AB13: =Z13-AA13 -> 8 | AC13: 0 | AD13: =AB13-AC13 -> 8 | AE13: 1 | AF13: =AD13-AE13 -> 7 | AG13: 2 | AH13: =AF13-AG13 -> 5 | AI13: 1 | AJ13: =AH13-AI13 -> 4 | AK13: 3 | AL13: =AJ13-AK13 -> 1 | AM13: 0 | AN13: =AL13-AM13 -> 1 | AO13: 0 | AP13: =AN13-AO13 -> 1 | AQ13: 1 | AR13: =AP13-AQ13 -> 0 | AS13: 0 | AT13: =AR13-AS13 -> 0 | AU13: 0 | AV13: =AT13-AU13 -> 0 | AW13: 0 | AX13: =AV13-AW13 -> 0 | AY13: 0 | AZ13: =AX13-AY13 -> 0 | BB13: =AY13+AW13+AU13+AS13+AQ13+AO13+AM13+AK13+AI13+AG13+AE13+AC13+AA13+Y13+W13+U13+S13+Q13+O13+M13+K13 -> 8 | BC13: =$BB13*D13 -> 8 | BD13: =BC13*F13 -> 0 | BE13: =BD13*G13 -> 0 | BF13: =$BB13*E13 -> 0 | BG13: =$BB13*H13 -> 0
C14: Validation | D14: 1 | E14: 0 | F14: 0 | G14: 0 | H14: =1-D14-E14 -> 0 | I14: 2 | J14: =I14 -> 2 | K14: 0 | L14: =J14-K14 -> 2 | M14: 0 | N14: =L14-M14 -> 2 | O14: 0 | P14: =N14-O14 -> 2 | Q14: 0 | R14: =P14-Q14 -> 2 | S14: 0 | T14: =R14-S14 -> 2 | V14: =T14-U14 -> 2 | X14: =V14-W14 -> 2 | Z14: =X14-Y14 -> 2 | AB14: =Z14-AA14 -> 2 | AD14: =AB14-AC14 -> 2 | AF14: =AD14-AE14 -> 2 | AH14: =AF14-AG14 -> 2 | AJ14: =AH14-AI14 -> 2 | AK14: 2 | AL14: 3 | AM14: 1 | AN14: =AL14-AM14 -> 2 | AO14: 0 | AP14: =AN14-AO14 -> 2 | AQ14: 2 | AR14: 4 | AS14: 2 | AT14: =AR14-AS14 -> 2 | AU14: 0 | AV14: =AT14-AU14 -> 2 | AW14: 0 | AX14: =AV14-AW14 -> 2 | AY14: 2 | AZ14: =AX14-AY14 -> 0 | BB14: =AY14+AW14+AU14+AS14+AQ14+AO14+AM14+AK14+AI14+AG14+AE14+AC14+AA14+Y14+W14+U14+S14+Q14+O14+M14+K14 -> 9 | BC14: =$BB14*D14 -> 9 | BD14: =BC14*F14 -> 0 | BE14: =BD14*G14 -> 0 | BF14: =$BB14*E14 -> 0 | BG14: =$BB14*H14 -> 0
C15: Setup de Xcode | D15: 1 | E15: 0 | F15: 0 | G15: 0 | H15: =1-D15-E15 -> 0 | I15: 5 | J15: =I15 -> 5 | K15: 0 | L15: =J15-K15 -> 5 | M15: 0 | N15: =L15-M15 -> 5 | O15: 0 | P15: =N15-O15 -> 5 | Q15: 0 | R15: =P15-Q15 -> 5 | S15: 0 | T15: =R15-S15 -> 5 | U15: 0 | V15: =T15-U15 -> 5 | W15: 0 | X15: =V15-W15 -> 5 | Y15: 0 | Z15: =X15-Y15 -> 5 | AA15: 0 | AB15: =Z15-AA15 -> 5 | AC15: 0 | AD15: =AB15-AC15 -> 5 | AE15: 0 | AF15: =AD15-AE15 -> 5 | AG15: 0 | AH15: =AF15-AG15 -> 5 | AI15: 0 | AJ15: =AH15-AI15 -> 5 | AK15: 3 | AL15: =AJ15-AK15 -> 2 | AM15: 2 | AN15: =AL15-AM15 -> 0 | AO15: 0 | AP15: =AN15-AO15 -> 0 | AQ15: 0 | AR15: =AP15-AQ15 -> 0 | AS15: 0 | AT15: =AR15-AS15 -> 0 | AU15: 0 | AV15: =AT15-AU15 -> 0 | AW15: 0 | AX15: =AV15-AW15 -> 0 | AY15: 0 | AZ15: =AX15-AY15 -> 0 | BB15: =AY15+AW15+AU15+AS15+AQ15+AO15+AM15+AK15+AI15+AG15+AE15+AC15+AA15+Y15+W15+U15+S15+Q15+O15+M15+K15 -> 5 | BC15: =$BB15*D15 -> 5 | BD15: =BC15*F15 -> 0 | BE15: =BD15*G15 -> 0 | BF15: =$BB15*E15 -> 0 | BG15: =$BB15*H15 -> 0
B16: 2 | C16: Création du profil d'utilisateur | D16: 1
C17: Création de la page principal pour afficher les options pour utilisateur | D17: 1 | E17: 0 | F17: 0 | G17: 0 | H17: =1-D17-E17 -> 0 | I17: 6 | J17: =I17 -> 6 | K17: 0 | L17: =J17-K17 -> 6 | M17: 0 | N17: =L17-M17 -> 6 | O17: 0 | P17: =N17-O17 -> 6 | Q17: 0 | R17: =P17-Q17 -> 6 | S17: 0 | T17: =R17-S17 -> 6 | U17: 0 | V17: =T17-U17 -> 6 | W17: 0 | X17: =V17-W17 -> 6 | Y17: 0 | Z17: =X17-Y17 -> 6 | AA17: 0 | AB17: =Z17-AA17 -> 6 | AC17: 0 | AD17: =AB17-AC17 -> 6 | AE17: 0 | AF17: =AD17-AE17 -> 6 | AG17: 0 | AH17: =AF17-AG17 -> 6 | AI17: 0 | AJ17: =AH17-AI17 -> 6 | AK17: 0 | AL17: =AJ17-AK17 -> 6 | AM17: 0 | AN17: =AL17-AM17 -> 6 | AO17: 0 | AP17: =AN17-AO17 -> 6 | AQ17: 0 | AR17: =AP17-AQ17 -> 6 | AS17: 0 | AT17: =AR17-AS17 -> 6 | AU17: 0 | AV17: =AT17-AU17 -> 6 | AW17: 0 | AX17: =AV17-AW17 -> 6 | AY17: 0 | AZ17: =AX17-AY17 -> 6 | BB17: 5 | BC17: =$BB17*D17 -> 5 | BD17: =BC17*F17 -> 0 | BE17: =BD17*G17 -> 0 | BF17: =$BB17*E17 -> 0 | BG17: =$BB17*H17 -> 0
C18: Ajouter la possiblité de faire les changements dans le dossier (ex:ajouter image profil, dark mode, profile details) | D18: 1 | E18: 0 | F18: 0 | G18: 0 | H18: =1-D18-E18 -> 0 | I18: 6 | J18: =I18 -> 6 | K18: 0 | L18: =J18-K18 -> 6 | M18: 0 | N18: =L18-M18 -> 6 | O18: 0 | P18: =N18-O18 -> 6 | Q18: 0 | R18: =P18-Q18 -> 6 | S18: 0 | T18: =R18-S18 -> 6 | U18: 0 | V18: =T18-U18 -> 6 | W18: 0 | X18: =V18-W18 -> 6 | Y18: 0 | Z18: =X18-Y18 -> 6 | AA18: 0 | AB18: =Z18-AA18 -> 6 | AC18: 0 | AD18: =AB18-AC18 -> 6 | AE18: 0 | AF18: =AD18-AE18 -> 6 | AG18: 0 | AH18: =AF18-AG18 -> 6 | AI18: 0 | AJ18: =AH18-AI18 -> 6 | AK18: 0 | AL18: =AJ18-AK18 -> 6 | AM18: 0 | AN18: =AL18-AM18 -> 6 | AO18: 0 | AP18: =AN18-AO18 -> 6 | AQ18: 0 | AR18: =AP18-AQ18 -> 6 | AS18: 0 | AT18: =AR18-AS18 -> 6 | AU18: 0 | AV18: =AT18-AU18 -> 6 | AW18: 0 | AX18: =AV18-AW18 -> 6 | AY18: 0 | AZ18: =AX18-AY18 -> 6 | BB18: 4 | BC18: =$BB18*D18 -> 4 | BD18: =BC18*F18 -> 0 | BE18: =BD18*G18 -> 0 | BF18: =$BB18*E18 -> 0 | BG18: =$BB18*H18 -> 0
C19: Visualisation du menu pour utilisauter | D19: 1 | E19: 0 | F19: 0 | G19: 0 | H19: =1-D19-E19 -> 0 | I19: 4 | J19: =I19 -> 4 | K19: 0 | L19: =J19-K19 -> 4 | M19: 0 | N19: =L19-M19 -> 4 | O19: 0 | P19: =N19-O19 -> 4 | Q19: 0 | R19: =P19-Q19 -> 4 | S19: 0 | T19: =R19-S19 -> 4 | U19: 0 | V19: =T19-U19 -> 4 | W19: 0 | X19: =V19-W19 -> 4 | Y19: 0 | Z19: =X19-Y19 -> 4 | AA19: 0 | AB19: =Z19-AA19 -> 4 | AC19: 0 | AD19: =AB19-AC19 -> 4 | AE19: 0 | AF19: =AD19-AE19 -> 4 | AG19: 0 | AH19: =AF19-AG19 -> 4 | AI19: 0 | AJ19: =AH19-AI19 -> 4 | AK19: 0 | AL19: =AJ19-AK19 -> 4 | AM19: 0 | AN19: =AL19-AM19 -> 4 | AO19: 0 | AP19: =AN19-AO19 -> 4 | AQ19: 0 | AR19: =AP19-AQ19 -> 4 | AS19: 0 | AT19: =AR19-AS19 -> 4 | AU19: 0 | AV19: =AT19-AU19 -> 4 | AW19: 0 | AX19: =AV19-AW19 -> 4 | AY19: 0 | AZ19: =AX19-AY19 -> 4 | BB19: 3 | BC19: =$BB19*D19 -> 3 | BD19: =BC19*F19 -> 0 | BE19: =BD19*G19 -> 0 | BF19: =$BB19*E19 -> 0 | BG19: =$BB19*H19 -> 0
C20: Creation de la base de données pour sauvegarder les information personnels | D20: 1 | E20: 0 | F20: 0 | G20: 0 | H20: =1-D20-E20 -> 0 | I20: 8 | J20: =I20 -> 8 | K20: 0 | L20: =J20-K20 -> 8 | M20: 0 | N20: =L20-M20 -> 8 | O20: 0 | P20: =N20-O20 -> 8 | Q20: 0 | R20: =P20-Q20 -> 8 | S20: 0 | T20: =R20-S20 -> 8 | U20: 0 | V20: =T20-U20 -> 8 | W20: 0 | X20: =V20-W20 -> 8 | Y20: 0 | Z20: =X20-Y20 -> 8 | AA20: 0 | AB20: =Z20-AA20 -> 8 | AC20: 0 | AD20: =AB20-AC20 -> 8 | AE20: 0 | AF20: =AD20-AE20 -> 8 | AG20: 0 | AH20: =AF20-AG20 -> 8 | AI20: 4 | AJ20: =AH20-AI20 -> 4 | AK20: 0 | AL20: =AJ20-AK20 -> 4 | AM20: 0 | AN20: =AL20-AM20 -> 4 | AO20: 4 | AP20: =AN20-AO20 -> 0 | AQ20: 0 | AR20: =AP20-AQ20 -> 0 | AS20: 0 | AT20: =AR20-AS20 -> 0 | AU20: 0 | AV20: =AT20-AU20 -> 0 | AW20: 0 | AX20: =AV20-AW20 -> 0 | AY20: 0 | AZ20: =AX20-AY20 -> 0 | BB20: =AY20+AW20+AU20+AS20+AQ20+AO20+AM20+AK20+AI20+AG20+AE20+AC20+AA20+Y20+W20+U20+S20+Q20+O20+M20+K20 -> 8 | BC20: =$BB20*D20 -> 8 | BD20: =BC20*F20 -> 0 | BE20: =BD20*G20 -> 0 | BF20: =$BB20*E20 -> 0 | BG20: =$BB20*H20 -> 0
B21: 3 | C21: Gestion du cours (ajout) | H21: 1
C22: Ajouter cours (code, nom) | D22: 0 | E22: 0 | F22: 0 | G22: 0 | H22: 1 | I22: 7 | J22: =I22 -> 7 | K22: 0 | L22: =J22-K22 -> 7 | M22: 0 | N22: =L22-M22 -> 7 | O22: 0 | P22: =N22-O22 -> 7 | Q22: 0 | R22: =P22-Q22 -> 7 | S22: 0 | T22: =R22-S22 -> 7 | U22: 0 | V22: =T22-U22 -> 7 | W22: 0 | X22: =V22-W22 -> 7 | Y22: 1 | Z22: =X22-Y22 -> 6 | AA22: 0 | AB22: =Z22-AA22 -> 6 | AC22: 0 | AD22: =AB22-AC22 -> 6 | AE22: 1 | AF22: =AD22-AE22 -> 5 | AG22: 3 | AH22: =AF22-AG22 -> 2 | AI22: 0 | AJ22: =AH22-AI22 -> 2 | AK22: 2 | AL22: =AJ22-AK22 -> 0 | AM22: 0 | AN22: =AL22-AM22 -> 0 | AO22: 0 | AP22: 2 | AQ22: 1 | AR22: =AP22-AQ22 -> 1 | AS22: 0 | AT22: =AR22-AS22 -> 1 | AU22: 1 | AV22: =AT22-AU22 -> 0 | AX22: =AV22-AW22 -> 0 | AZ22: =AX22-AY22 -> 0 | BB22: =AY22+AW22+AU22+AS22+AQ22+AO22+AM22+AK22+AI22+AG22+AE22+AC22+AA22+Y22+W22+U22+S22+Q22+O22+M22+K22 -> 9 | BC22: =$BB22*D22 -> 0 | BD22: =BC22*F22 -> 0 | BE22: =BD22*G22 -> 0 | BF22: =$BB22*E22 -> 0 | BG22: =$BB22*H22 -> 9
C23: Sauvegarder le cours | D23: 0 | E23: 0 | F23: 0 | G23: 0 | H23: 1 | I23: 3 | J23: =I23 -> 3 | K23: 0 | L23: =J23-K23 -> 3 | M23: 0 | N23: =L23-M23 -> 3 | O23: 0 | P23: =N23-O23 -> 3 | Q23: 0 | R23: =P23-Q23 -> 3 | S23: 0 | T23: =R23-S23 -> 3 | U23: 0 | V23: =T23-U23 -> 3 | W23: 0 | X23: =V23-W23 -> 3 | Y23: 0 | Z23: =X23-Y23 -> 3 | AA23: 0 | AB23: =Z23-AA23 -> 3 | AC23: 0 | AD23: =AB23-AC23 -> 3 | AE23: 0 | AF23: =AD23-AE23 -> 3 | AG23: 0 | AH23: =AF23-AG23 -> 3 | AI23: 1 | AJ23: =AH23-AI23 -> 2 | AK23: 0 | AL23: =AJ23-AK23 -> 2 | AM23: 0 | AN23: =AL23-AM23 -> 2 | AO23: 0 | AP23: =AN23-AO23 -> 2 | AQ23: 1 | AR23: =AP23-AQ23 -> 1 | AS23: 0 | AT23: =AR23-AS23 -> 1 | AU23: 0 | AV23: 1 | AW23: 1 | AX23: =AV23-AW23 -> 0 | AY23: 0 | AZ23: 0 | BB23: =AY23+AW23+AU23+AS23+AQ23+AO23+AM23+AK23+AI23+AG23+AE23+AC23+AA23+Y23+W23+U23+S23+Q23+O23+M23+K23 -> 3 | BC23: 0 | BD23: 0 | BE23: 0 | BF23: 0 | BG23: =$BB23*H23 -> 3
C24: Afficher la liste des cours après ajout | D24: 0 | E24: 0 | F24: 0 | G24: 0 | H24: 1 | I24: 4 | J24: 0 | K24: 0 | L24: 0 | M24: 0 | N24: 0 | O24: 0 | P24: 0 | Q24: 0 | R24: 0 | S24: 0 | T24: 0 | U24: 0 | V24: 0 | W24: 0 | X24: 0 | Y24: 0 | Z24: 0 | AA24: 0 | AB24: 0 | AC24: 0 | AD24: 0 | AE24: 0 | AF24: 0 | AG24: 0 | AH24: 0 | AI24: 0 | AJ24: 0 | AK24: 0 | AL24: 0 | AM24: 0 | AN24: 0 | AO24: 1 | AP24: 3 | AQ24: 1 | AR24: 2 | AS24: 0 | AT24: 2 | AU24: 0 | AV24: 2 | AW24: 2 | AX24: 0 | AY24: 0 | AZ24: 0 | BB24: =AY24+AW24+AU24+AS24+AQ24+AO24+AM24+AK24+AI24+AG24+AE24+AC24+AA24+Y24+W24+U24+S24+Q24+O24+M24+K24 -> 4 | BC24: 0 | BD24: 0 | BE24: 0 | BF24: 0 | BG24: =$BB24*H24 -> 4
B25: 4 | C25: Gestion du cours (seuil du passage) | H25: 1
C26: Attribuer un pourcentage de passage à un cours | D26: 0 | E26: 0 | F26: 0 | G26: 0 | H26: 1 | I26: 2 | J26: =I26 -> 2 | K26: 0 | L26: =J26-K26 -> 2 | M26: 0 | N26: =L26-M26 -> 2 | O26: 0 | P26: =N26-O26 -> 2 | Q26: 0 | R26: =P26-Q26 -> 2 | S26: 0 | T26: =R26-S26 -> 2 | U26: 0 | V26: =T26-U26 -> 2 | W26: 0 | X26: =V26-W26 -> 2 | Y26: 0 | Z26: =X26-Y26 -> 2 | AA26: 0 | AB26: =Z26-AA26 -> 2 | AC26: 0 | AD26: =AB26-AC26 -> 2 | AE26: 0 | AF26: =AD26-AE26 -> 2 | AG26: 0 | AH26: =AF26-AG26 -> 2 | AI26: 0 | AJ26: =AH26-AI26 -> 2 | AK26: 0 | AL26: =AJ26-AK26 -> 2 | AM26: 2 | AN26: =AL26-AM26 -> 0 | AO26: 0 | AP26: =AN26-AO26 -> 0 | AQ26: 0 | AR26: =AP26-AQ26 -> 0 | AS26: 0 | AT26: =AR26-AS26 -> 0 | AU26: 0 | AV26: 2 | AW26: 2 | AX26: =AV26-AW26 -> 0 | AZ26: =AX26-AY26 -> 0 | BB26: =AY26+AW26+AU26+AS26+AQ26+AO26+AM26+AK26+AI26+AG26+AE26+AC26+AA26+Y26+W26+U26+S26+Q26+O26+M26+K26 -> 4 | BC26: =$BB26*D26 -> 0 | BD26: =BC26*F26 -> 0 | BE26: =BD26*G26 -> 0 | BF26: =$BB26*E26 -> 0 | BG26: =$BB26*H26 -> 4
B27: 5 | C27: Gestion du cours (suppression ou modification) | H27: 1 | BD27: =BC27*F27 -> 0 | BE27: =BD27*G27 -> 0
C28: Modifier un cours existant | D28: 0 | E28: 0 | F28: 0 | G28: 0 | H28: 1 | I28: 3 | J28: =I28 -> 3 | K28: 0 | L28: =J28-K28 -> 3 | M28: 0 | N28: =L28-M28 -> 3 | O28: 0 | P28: =N28-O28 -> 3 | Q28: 0 | R28: =P28-Q28 -> 3 | S28: 0 | T28: =R28-S28 -> 3 | U28: 0 | V28: =T28-U28 -> 3 | W28: 0 | X28: =V28-W28 -> 3 | Y28: 0 | Z28: =X28-Y28 -> 3 | AA28: 0 | AB28: =Z28-AA28 -> 3 | AC28: 0 | AD28: =AB28-AC28 -> 3 | AE28: 0 | AF28: =AD28-AE28 -> 3 | AG28: 0 | AH28: =AF28-AG28 -> 3 | AI28: 0 | AJ28: =AH28-AI28 -> 3 | AK28: 0 | AL28: =AJ28-AK28 -> 3 | AM28: 0 | AN28: =AL28-AM28 -> 3 | AO28: 0 | AP28: =AN28-AO28 -> 3 | AQ28: 0 | AR28: =AP28-AQ28 -> 3 | AS28: 2 | AT28: 0 | AV28: =AT28-AU28 -> 0 | AX28: =AV28-AW28 -> 0 | AZ28: =AX28-AY28 -> 0 | BB28: =AY28+AW28+AU28+AS28+AQ28+AO28+AM28+AK28+AI28+AG28+AE28+AC28+AA28+Y28+W28+U28+S28+Q28+O28+M28+K28 -> 2 | BC28: =$BB28*D28 -> 0 | BD28: =BC28*F28 -> 0 | BE28: =BD28*G28 -> 0 | BF28: =$BB28*E28 -> 0 | BG28: =$BB28*H28 -> 2
C29: Supprimer un cours (ex. abandonné) | D29: 0 | E29: 0 | F29: 0 | G29: 0 | H29: 1 | I29: 3 | J29: =I29 -> 3 | K29: 0 | L29: =J29-K29 -> 3 | M29: 0 | N29: =L29-M29 -> 3 | O29: 0 | P29: =N29-O29 -> 3 | Q29: 0 | R29: =P29-Q29 -> 3 | S29: 0 | T29: =R29-S29 -> 3 | U29: 0 | V29: =T29-U29 -> 3 | W29: 0 | X29: =V29-W29 -> 3 | Y29: 0 | Z29: =X29-Y29 -> 3 | AA29: 0 | AB29: =Z29-AA29 -> 3 | AC29: 0 | AD29: =AB29-AC29 -> 3 | AE29: 0 | AF29: =AD29-AE29 -> 3 | AG29: 0 | AH29: =AF29-AG29 -> 3 | AI29: 0 | AJ29: =AH29-AI29 -> 3 | AK29: 0 | AL29: =AJ29-AK29 -> 3 | AM29: 0 | AN29: =AL29-AM29 -> 3 | AO29: 0 | AP29: =AN29-AO29 -> 3 | AQ29: 0 | AR29: =AP29-AQ29 -> 3 | AS29: 0 | AT29: =AR29-AS29 -> 3 | AU29: 2 | AV29: 0 | AX29: =AV29-AW29 -> 0 | AZ29: =AX29-AY29 -> 0 | BB29: =AY29+AW29+AU29+AS29+AQ29+AO29+AM29+AK29+AI29+AG29+AE29+AC29+AA29+Y29+W29+U29+S29+Q29+O29+M29+K29 -> 2 | BC29: =$BB29*D29 -> 0 | BD29: =BC29*F29 -> 0 | BE29: =BD29*G29 -> 0 | BF29: =$BB29*E29 -> 0 | BG29: =$BB29*H29 -> 2
B30: 6 | C30: Ajout des échéances | G30: 1
C31: Connexion à la bd via API supabase | D31: 0 | E31: 0 | F31: 0 | G31: 1 | H31: 0 | I31: 5 | J31: =I31 -> 5 | K31: 0 | L31: =J31-K31 -> 5 | M31: 0 | N31: =L31-M31 -> 5 | O31: 0 | P31: =N31-O31 -> 5 | Q31: 0 | R31: =P31-Q31 -> 5 | S31: 4 | T31: 0 | U31: 0 | V31: =T31-U31 -> 0 | W31: 0 | X31: =V31-W31 -> 0 | Y31: 1 | Z31: 0 | AA31: 0 | AB31: 0 | AC31: 0 | AD31: =AB31-AC31 -> 0 | AE31: 0 | AF31: =AD31-AE31 -> 0 | AG31: 0 | AH31: =AF31-AG31 -> 0 | AI31: 0 | AJ31: =AH31-AI31 -> 0 | AK31: 0 | AL31: =AJ31-AK31 -> 0 | AM31: 0 | AN31: =AL31-AM31 -> 0 | AO31: 0 | AP31: =AN31-AO31 -> 0 | AQ31: 0 | AR31: =AP31-AQ31 -> 0 | AS31: 0 | AT31: =AR31-AS31 -> 0 | AU31: 0 | AV31: =AT31-AU31 -> 0 | AW31: 0 | AX31: =AV31-AW31 -> 0 | AY31: 0 | AZ31: =AX31-AY31 -> 0 | BB31: =AY31+AW31+AU31+AS31+AQ31+AO31+AM31+AK31+AI31+AG31+AE31+AC31+AA31+Y31+W31+U31+S31+Q31+O31+M31+K31 -> 5 | BC31: =$BB31*D31 -> 0 | BD31: =BC31*F31 -> 0 | BE31: =$BB31*G31 -> 5 | BF31: =$BB31*E31 -> 0 | BG31: =$BB31*H31 -> 0
C32: Setup de Android studio | D32: 0 | E32: 0 | F32: 0 | G32: 1 | H32: 0 | I32: 3 | J32: 3 | K32: 0 | L32: 3 | M32: 0 | N32: 3 | O32: 0 | P32: 3 | Q32: 0 | R32: 3 | S32: 2 | T32: 1 | U32: 4 | V32: 0 | W32: 0 | X32: 0 | Y32: 0 | Z32: =X32-Y32 -> 0 | AA32: 0 | AB32: =Z32-AA32 -> 0 | AC32: 0 | AD32: =AB32-AC32 -> 0 | AE32: 0 | AF32: =AD32-AE32 -> 0 | AG32: 0 | AH32: =AF32-AG32 -> 0 | AI32: 0 | AJ32: =AH32-AI32 -> 0 | AK32: 0 | AL32: =AJ32-AK32 -> 0 | AM32: 0 | AN32: =AL32-AM32 -> 0 | AO32: 0 | AP32: =AN32-AO32 -> 0 | AQ32: 0 | AR32: =AP32-AQ32 -> 0 | AS32: 0 | AT32: =AR32-AS32 -> 0 | AU32: 0 | AV32: =AT32-AU32 -> 0 | AW32: 0 | AX32: =AV32-AW32 -> 0 | AY32: 0 | AZ32: =AX32-AY32 -> 0 | BB32: =AY32+AW32+AU32+AS32+AQ32+AO32+AM32+AK32+AI32+AG32+AE32+AC32+AA32+Y32+W32+U32+S32+Q32+O32+M32+K32 -> 6 | BC32: 0 | BD32: =BC32*F32 -> 0 | BE32: =$BB32*G32 -> 6 | BF32: 0 | BG32: 0
C33: Création de la page des échéances | D33: 0 | E33: 0 | F33: 0 | G33: 1 | H33: 0 | I33: 5 | J33: =I33 -> 5 | K33: 0 | L33: =J33-K33 -> 5 | M33: 0 | N33: =L33-M33 -> 5 | O33: 0 | P33: =N33-O33 -> 5 | Q33: 0 | R33: =P33-Q33 -> 5 | S33: 2 | T33: =R33-S33 -> 3 | U33: 0 | V33: =T33-U33 -> 3 | W33: 2 | X33: 3 | Y33: 2 | Z33: =X33-Y33 -> 1 | AA33: 1 | AB33: =Z33-AA33 -> 0 | AC33: 0 | AD33: 0 | AE33: 0 | AF33: =AD33-AE33 -> 0 | AG33: 0 | AH33: 0 | AI33: 0 | AJ33: =AH33-AI33 -> 0 | AK33: 0 | AL33: =AJ33-AK33 -> 0 | AM33: 0 | AN33: 0 | AO33: 0 | AP33: =AN33-AO33 -> 0 | AQ33: 0 | AR33: 0 | AS33: 0 | AT33: =AR33-AS33 -> 0 | AU33: 0 | AV33: =AT33-AU33 -> 0 | AW33: 0 | AX33: =AV33-AW33 -> 0 | AY33: 0 | AZ33: =AX33-AY33 -> 0 | BB33: =AY33+AW33+AU33+AS33+AQ33+AO33+AM33+AK33+AI33+AG33+AE33+AC33+AA33+Y33+W33+U33+S33+Q33+O33+M33+K33 -> 7 | BC33: =$BB33*D33 -> 0 | BD33: =BC33*F33 -> 0 | BE33: =$BB33*G33 -> 7 | BF33: =$BB33*E33 -> 0 | BG33: =$BB33*H33 -> 0
C34: Création de l'ajout des échéances | D34: 0 | E34: 0 | F34: 0 | G34: 1 | H34: 0 | I34: 8 | J34: =I34 -> 8 | K34: 0 | L34: =J34-K34 -> 8 | M34: 0 | N34: =L34-M34 -> 8 | O34: 0 | P34: =N34-O34 -> 8 | Q34: 0 | R34: =P34-Q34 -> 8 | S34: 2 | T34: =R34-S34 -> 6 | U34: 0 | V34: =T34-U34 -> 6 | W34: 3 | X34: =V34-W34 -> 3 | Y34: 2 | Z34: 3 | AA34: 1 | AB34: =Z34-AA34 -> 2 | AC34: 1 | AD34: =AB34-AC34 -> 1 | AE34: 1 | AF34: =AD34-AE34 -> 0 | AG34: 0 | AH34: =AF34-AG34 -> 0 | AI34: 0 | AJ34: =AH34-AI34 -> 0 | AK34: 0 | AL34: =AJ34-AK34 -> 0 | AM34: 0 | AN34: =AL34-AM34 -> 0 | AO34: 0 | AP34: =AN34-AO34 -> 0 | AQ34: 0 | AR34: =AP34-AQ34 -> 0 | AS34: 0 | AT34: =AR34-AS34 -> 0 | AU34: 0 | AV34: =AT34-AU34 -> 0 | AW34: 0 | AX34: =AV34-AW34 -> 0 | AY34: 0 | AZ34: =AX34-AY34 -> 0 | BB34: =AY34+AW34+AU34+AS34+AQ34+AO34+AM34+AK34+AI34+AG34+AE34+AC34+AA34+Y34+W34+U34+S34+Q34+O34+M34+K34 -> 10 | BC34: =$BB34*D34 -> 0 | BD34: =BC34*F34 -> 0 | BE34: =$BB34*G34 -> 10 | BF34: =$BB34*E34 -> 0 | BG34: =$BB34*H34 -> 0
B35: 7 | C35: Modification des échéances | G35: 1
C36: Ajout de modification des échéances | D36: 0 | E36: 0 | F36: 0 | G36: 1 | H36: 0 | I36: 6 | J36: =I36 -> 6 | K36: 0 | L36: =J36-K36 -> 6 | M36: 0 | N36: =L36-M36 -> 6 | O36: 0 | P36: =N36-O36 -> 6 | Q36: 0 | R36: =P36-Q36 -> 6 | S36: 0 | T36: =R36-S36 -> 6 | U36: 0 | V36: =T36-U36 -> 6 | W36: 0 | X36: =V36-W36 -> 6 | Y36: 0 | Z36: =X36-Y36 -> 6 | AA36: 0 | AB36: =Z36-AA36 -> 6 | AC36: 0 | AD36: =AB36-AC36 -> 6 | AE36: 0 | AF36: =AD36-AE36 -> 6 | AG36: 2 | AH36: =AF36-AG36 -> 4 | AI36: 0 | AJ36: =AH36-AI36 -> 4 | AK36: 1 | AL36: =AJ36-AK36 -> 3 | AM36: 2 | AN36: 2 | AO36: 1 | AP36: =AN36-AO36 -> 1 | AQ36: 1 | AR36: =AP36-AQ36 -> 0 | AS36: 0 | AT36: =AR36-AS36 -> 0 | AU36: 0 | AV36: =AT36-AU36 -> 0 | AW36: 0 | AX36: =AV36-AW36 -> 0 | AY36: 0 | AZ36: =AX36-AY36 -> 0 | BB36: =AY36+AW36+AU36+AS36+AQ36+AO36+AM36+AK36+AI36+AG36+AE36+AC36+AA36+Y36+W36+U36+S36+Q36+O36+M36+K36 -> 7 | BC36: =$BB36*D36 -> 0 | BD36: =BC36*F36 -> 0 | BE36: =$BB36*G36 -> 7 | BF36: =$BB36*E36 -> 0 | BG36: =$BB36*H36 -> 0
C37: Ajout de suppression des échéances | D37: 0 | E37: 0 | F37: 0 | G37: 1 | H37: 0 | I37: 6 | J37: =I37 -> 6 | K37: 0 | L37: =J37-K37 -> 6 | M37: 0 | N37: =L37-M37 -> 6 | O37: 0 | P37: =N37-O37 -> 6 | Q37: 0 | R37: =P37-Q37 -> 6 | S37: 0 | T37: =R37-S37 -> 6 | U37: 0 | V37: =T37-U37 -> 6 | W37: 0 | X37: =V37-W37 -> 6 | Y37: 0 | Z37: =X37-Y37 -> 6 | AA37: 0 | AB37: =Z37-AA37 -> 6 | AC37: 0 | AD37: =AB37-AC37 -> 6 | AE37: 0 | AF37: =AD37-AE37 -> 6 | AG37: 1 | AH37: =AF37-AG37 -> 5 | AI37: 0 | AJ37: =AH37-AI37 -> 5 | AK37: 1 | AL37: =AJ37-AK37 -> 4 | AM37: 1 | AN37: =AL37-AM37 -> 3 | AO37: 1 | AP37: =AN37-AO37 -> 2 | AQ37: 1 | AR37: =AP37-AQ37 -> 1 | AS37: 1 | AT37: =AR37-AS37 -> 0 | AU37: 0 | AV37: =AT37-AU37 -> 0 | AW37: 0 | AX37: =AV37-AW37 -> 0 | AY37: 0 | AZ37: =AX37-AY37 -> 0 | BB37: =AY37+AW37+AU37+AS37+AQ37+AO37+AM37+AK37+AI37+AG37+AE37+AC37+AA37+Y37+W37+U37+S37+Q37+O37+M37+K37 -> 6 | BC37: =$BB37*D37 -> 0 | BD37: =BC37*F37 -> 0 | BE37: =$BB37*G37 -> 6 | BF37: =$BB37*E37 -> 0 | BG37: =$BB37*H37 -> 0
B38: 8 | C38: Vue calendrier hebdomadaire : Affichage des examens, quiz, paiement à travers une globale du calendrier | D38: 0.25 | E38: 0.75
C39: Création du calendrier basique | D39: 0 | E39: 1 | F39: 0 | G39: 0 | H39: 0 | I39: 5 | J39: =I39 -> 5 | K39: 1 | L39: =J39-K39 -> 4 | M39: 0 | N39: =L39-M39 -> 4 | O39: 0 | P39: =N39-O39 -> 4 | Q39: 3 | R39: 5 | S39: 0 | T39: =R39-S39 -> 5 | U39: 0 | V39: =T39-U39 -> 5 | W39: 3 | X39: =V39-W39 -> 2 | Y39: 0 | Z39: =X39-Y39 -> 2 | AA39: 0 | AB39: =Z39-AA39 -> 2 | AC39: 0 | AD39: =AB39-AC39 -> 2 | AE39: 2 | AF39: 3 | AG39: 1 | AH39: =AF39-AG39 -> 2 | AI39: 0 | AJ39: =AH39-AI39 -> 2 | AK39: 0 | AL39: =AJ39-AK39 -> 2 | AM39: 0 | AN39: =AL39-AM39 -> 2 | AO39: 0 | AP39: =AN39-AO39 -> 2 | AQ39: 0 | AR39: =AP39-AQ39 -> 2 | AS39: 2 | AT39: 0 | AU39: 0 | AV39: =AT39-AU39 -> 0 | AW39: 0 | AX39: =AV39-AW39 -> 0 | AY39: 0 | AZ39: =AX39-AY39 -> 0 | BB39: =AY39+AW39+AU39+AS39+AQ39+AO39+AM39+AK39+AI39+AG39+AE39+AC39+AA39+Y39+W39+U39+S39+Q39+O39+M39+K39 -> 12 | BC39: =$BB39*D39 -> 0 | BD39: =BC39*F39 -> 0 | BE39: =BB39*G39 -> 0 | BF39: =$BB39*E39 -> 12 | BG39: =$BB39*H39 -> 0
C40: Ajout de la rubrique évènements à venir | D40: 0 | E40: 1 | F40: 0 | G40: 0 | H40: 0 | I40: 4 | J40: =I40 -> 4 | K40: 2 | L40: =J40-K40 -> 2 | M40: 0 | N40: =L40-M40 -> 2 | O40: 0 | P40: =N40-O40 -> 2 | Q40: 0 | R40: =P40-Q40 -> 2 | S40: 0 | T40: =R40-S40 -> 2 | U40: 0 | V40: =T40-U40 -> 2 | W40: 0 | X40: =V40-W40 -> 2 | Y40: 0 | Z40: =X40-Y40 -> 2 | AA40: 0 | AB40: =Z40-AA40 -> 2 | AC40: 0 | AD40: =AB40-AC40 -> 2 | AE40: 1 | AF40: =AD40-AE40 -> 1 | AG40: 0 | AH40: =AF40-AG40 -> 1 | AI40: 0 | AJ40: =AH40-AI40 -> 1 | AK40: 0 | AL40: =AJ40-AK40 -> 1 | AM40: 0 | AN40: =AL40-AM40 -> 1 | AO40: 1 | AP40: =AN40-AO40 -> 0 | AR40: =AP40-AQ40 -> 0 | AS40: 0 | AT40: =AR40-AS40 -> 0 | AU40: 0 | AV40: =AT40-AU40 -> 0 | AW40: 0 | AX40: =AV40-AW40 -> 0 | AY40: 0 | AZ40: =AX40-AY40 -> 0 | BB40: =AY40+AW40+AU40+AS40+AQ40+AO40+AM40+AK40+AI40+AG40+AE40+AC40+AA40+Y40+W40+U40+S40+Q40+O40+M40+K40 -> 4 | BC40: =$BB40*D40 -> 0 | BD40: =BC40*F40 -> 0 | BE40: =BB40*G40 -> 0 | BF40: =$BB40*E40 -> 4 | BG40: =$BB40*H40 -> 0
C41: Création de la vue globale | D41: 0.25 | E41: =E38 -> 0.75 | F41: 0 | G41: 0 | H41: 0 | I41: 5 | J41: =I41 -> 5 | K41: 1 | L41: =J41-K41 -> 4 | M41: 1 | N41: =L41-M41 -> 3 | O41: 0 | P41: =N41-O41 -> 3 | Q41: 0 | R41: =P41-Q41 -> 3 | S41: 1 | T41: =R41-S41 -> 2 | U41: 0 | V41: =T41-U41 -> 2 | W41: 0 | X41: =V41-W41 -> 2 | Y41: 0 | Z41: =X41-Y41 -> 2 | AA41: 0 | AB41: =Z41-AA41 -> 2 | AC41: 0 | AD41: =AB41-AC41 -> 2 | AE41: 1 | AF41: 3 | AG41: 0 | AH41: =AF41-AG41 -> 3 | AI41: 0 | AJ41: =AH41-AI41 -> 3 | AK41: 0 | AL41: =AJ41-AK41 -> 3 | AM41: 0 | AN41: =AL41-AM41 -> 3 | AO41: 0 | AP41: =AN41-AO41 -> 3 | AQ41: 0 | AR41: =AP41-AQ41 -> 3 | AS41: 3 | AT41: =AR41-AS41 -> 0 | AU41: 0 | AV41: 1 | AW41: 1 | AX41: =AV41-AW41 -> 0 | AY41: 0 | AZ41: =AX41-AY41 -> 0 | BB41: =AY41+AW41+AU41+AS41+AQ41+AO41+AM41+AK41+AI41+AG41+AE41+AC41+AA41+Y41+W41+U41+S41+Q41+O41+M41+K41 -> 8 | BC41: =$BB41*D41 -> 2 | BD41: =BC41*F41 -> 0 | BE41: =BB41*G41 -> 0 | BF41: =$BB41*E41 -> 6 | BG41: =$BB41*H41 -> 0
C42: Ajout de la possibilité de voir les évènements directement sur le calendrier | D42: 0 | E42: 1 | F42: 0 | G42: 0 | H42: 0 | I42: 5 | J42: 5 | K42: 0 | L42: =J42 -> 5 | M42: 0 | N42: 5 | O42: 1 | P42: =N42-O42 -> 4 | Q42: 1 | R42: =P42-Q42 -> 3 | S42: 0 | T42: =R42-S42 -> 3 | U42: 0 | V42: =T42-U42 -> 3 | W42: 0 | X42: =V42-W42 -> 3 | Y42: 0 | Z42: =X42-Y42 -> 3 | AA42: 1 | AB42: =Z42-AA42 -> 2 | AC42: 0 | AD42: =AB42-AC42 -> 2 | AE42: 0 | AF42: =AD42-AE42 -> 2 | AG42: 0 | AH42: =AF42-AG42 -> 2 | AI42: 0 | AJ42: =AH42-AI42 -> 2 | AK42: 1 | AL42: =AJ42-AK42 -> 1 | AM42: 0 | AN42: =AL42-AM42 -> 1 | AO42: 1 | AP42: =AN42-AO42 -> 0 | AQ42: 0 | AR42: =AP42-AQ42 -> 0 | AS42: 0 | AT42: =AR42-AS42 -> 0 | AU42: 0 | AV42: 1 | AW42: 1 | AX42: =AV42-AW42 -> 0 | AY42: 0 | AZ42: 0 | BB42: =AY42+AW42+AU42+AS42+AQ42+AO42+AM42+AK42+AI42+AG42+AE42+AC42+AA42+Y42+W42+U42+S42+Q42+O42+M42+K42 -> 6 | BC42: =$BB42*D42 -> 0 | BD42: =BC42*F42 -> 0 | BE42: =BB42*G42 -> 0 | BF42: =$BB42*E42 -> 6 | BG42: =$BB42*H42 -> 0
B43: 9 | C43: Ajout de la personnalisation du calendrier avec des couleurs au choix | D43: =D44 -> 0.25 | E43: =E44 -> 0.75
C44: Ajout du bouton de personnalisation | D44: 0.25 | E44: =100%-D44 -> 0.75 | F44: 0 | G44: 0 | H44: 0 | I44: 8 | J44: =I44 -> 8 | K44: 0 | L44: =J44-K44 -> 8 | M44: 0 | N44: =L44-M44 -> 8 | O44: 0 | P44: =N44-O44 -> 8 | Q44: 0 | R44: =P44-Q44 -> 8 | S44: 0 | T44: =R44-S44 -> 8 | U44: 0 | V44: =T44-U44 -> 8 | W44: 0 | X44: =V44-W44 -> 8 | Y44: 0 | Z44: =X44-Y44 -> 8 | AA44: 0 | AB44: =Z44-AA44 -> 8 | AC44: 0 | AD44: =AB44-AC44 -> 8 | AE44: 0 | AF44: =AD44-AE44 -> 8 | AG44: 0 | AH44: =AF44-AG44 -> 8 | AI44: 0 | AJ44: =AH44-AI44 -> 8 | AK44: 0 | AL44: =AJ44-AK44 -> 8 | AM44: 0 | AN44: =AL44-AM44 -> 8 | AO44: 0 | AP44: =AN44-AO44 -> 8 | AQ44: 0 | AR44: =AP44-AQ44 -> 8 | AS44: 0 | AT44: =AR44-AS44 -> 8 | AU44: 4 | AV44: =AT44-AU44 -> 4 | AW44: 4 | AX44: =AV44-AW44 -> 0 | AY44: 0 | AZ44: =AX44-AY44 -> 0 | BB44: =AY44+AW44+AU44+AS44+AQ44+AO44+AM44+AK44+AI44+AG44+AE44+AC44+AA44+Y44+W44+U44+S44+Q44+O44+M44+K44 -> 8 | BC44: =$BB44*D44 -> 2 | BD44: =BC44*F44 -> 0 | BE44: =BD44*G44 -> 0 | BF44: =$BB44*E44 -> 6 | BG44: =$BB44*H44 -> 0
C45: Ajout des couleurs aux choix | D45: 0 | E45: 1 | F45: 0 | G45: 0 | H45: 0 | I45: 3 | J45: =I45 -> 3 | K45: 0 | L45: =J45-K45 -> 3 | M45: 0 | N45: =L45-M45 -> 3 | O45: 0 | P45: =N45-O45 -> 3 | Q45: 0 | R45: =P45-Q45 -> 3 | S45: 0 | T45: =R45-S45 -> 3 | U45: 0 | V45: =T45-U45 -> 3 | W45: 0 | X45: =V45-W45 -> 3 | Y45: 0 | Z45: =X45-Y45 -> 3 | AA45: 0 | AB45: =Z45-AA45 -> 3 | AC45: 0 | AD45: =AB45-AC45 -> 3 | AE45: 0 | AF45: =AD45-AE45 -> 3 | AG45: 0 | AH45: =AF45-AG45 -> 3 | AI45: 0 | AJ45: =AH45-AI45 -> 3 | AK45: 0 | AL45: =AJ45-AK45 -> 3 | AM45: 0 | AN45: =AL45-AM45 -> 3 | AO45: 0 | AP45: =AN45-AO45 -> 3 | AQ45: 0 | AR45: =AP45-AQ45 -> 3 | AS45: 0 | AT45: =AR45-AS45 -> 3 | AU45: 0 | AV45: 4 | AW45: 4 | AX45: 0 | AY45: 0 | AZ45: =AX45-AY45 -> 0 | BB45: =AY45+AW45+AU45+AS45+AQ45+AO45+AM45+AK45+AI45+AG45+AE45+AC45+AA45+Y45+W45+U45+S45+Q45+O45+M45+K45 -> 4 | BC45: =$BB45*D45 -> 0 | BD45: =BC45*F45 -> 0 | BE45: =BD45*G45 -> 0 | BF45: =$BB45*E45 -> 4 | BG45: =$BB45*H45 -> 0
C46: Ajout de modifications de la police, gras, taille des lettres | D46: 0 | E46: 1 | F46: 0 | G46: 0 | H46: 0 | I46: 5 | J46: =I46 -> 5 | K46: 0 | L46: =J46-K46 -> 5 | M46: 0 | N46: =L46-M46 -> 5 | O46: 0 | P46: =N46-O46 -> 5 | Q46: 0 | R46: =P46-Q46 -> 5 | S46: 0 | T46: =R46-S46 -> 5 | U46: 0 | V46: =T46-U46 -> 5 | W46: 0 | X46: =V46-W46 -> 5 | Y46: 0 | Z46: =X46-Y46 -> 5 | AA46: 0 | AB46: =Z46-AA46 -> 5 | AC46: 0 | AD46: =AB46-AC46 -> 5 | AE46: 0 | AF46: =AD46-AE46 -> 5 | AG46: 0 | AH46: =AF46-AG46 -> 5 | AI46: 0 | AJ46: =AH46-AI46 -> 5 | AK46: 0 | AL46: =AJ46-AK46 -> 5 | AM46: 0 | AN46: =AL46-AM46 -> 5 | AO46: 0 | AP46: =AN46-AO46 -> 5 | AQ46: 0 | AR46: =AP46-AQ46 -> 5 | AS46: 0 | AT46: =AR46-AS46 -> 5 | AU46: 2 | AV46: =AT46-AU46 -> 3 | AW46: 3 | AX46: =AV46-AW46 -> 0 | AY46: 0 | AZ46: =AX46-AY46 -> 0 | BB46: =AY46+AW46+AU46+AS46+AQ46+AO46+AM46+AK46+AI46+AG46+AE46+AC46+AA46+Y46+W46+U46+S46+Q46+O46+M46+K46 -> 5 | BC46: =$BB46*D46 -> 0 | BD46: =BC46*F46 -> 0 | BE46: =BD46*G46 -> 0 | BF46: =$BB46*E46 -> 5 | BG46: =$BB46*H46 -> 0
B47: 10 | C47: Mise en place de la notification | D47: 0.25 | F47: 0.75
C48: Ajouter la possbilité d'avoir les notifiacations qui sont envoyer par le systeme | D48: 0 | E48: 0 | F48: 1 | G48: 0 | H48: 0 | I48: 3 | J48: =I48 -> 3 | K48: 3 | L48: 4 | M48: 4 | N48: 3 | O48: 3 | P48: =N48-O48 -> 0 | Q48: 0 | R48: =P48-Q48 -> 0 | S48: 0 | T48: 2 | U48: 2 | V48: 3 | W48: 3 | X48: 6 | Y48: 6 | Z48: 5 | AA48: 5 | AB48: 4 | AC48: 2 | AD48: =AB48-AC48 -> 2 | AE48: 2 | AF48: =AD48-AE48 -> 0 | AG48: 0 | AH48: 4 | AI48: 2 | AJ48: =AH48-AI48 -> 2 | AK48: 2 | AL48: 3 | AM48: 3 | AN48: =AL48-AM48 -> 0 | AO48: 0 | AP48: 6 | AQ48: 3 | AR48: =AP48-AQ48 -> 3 | AS48: 3 | AT48: 5 | AU48: 4 | AV48: 7 | AW48: 5 | AX48: =AV48-AW48 -> 2 | AY48: 3 | AZ48: =AX48-AY48 -> -1 | BB48: =AY48+AW48+AU48+AS48+AQ48+AO48+AM48+AK48+AI48+AG48+AE48+AC48+AA48+Y48+W48+U48+S48+Q48+O48+M48+K48 -> 55 | BC48: =$BB48*D48 -> 0 | BD48: =BB48*F48 -> 55 | BE48: =BD48*G48 -> 0 | BF48: =$BB48*E48 -> 0 | BG48: =$BB48*H48 -> 0
C49: Ajouter la focntionnalité pour la gestion des notificaitons - fréquence | D49: 0 | E49: 0 | F49: 1 | G49: 0 | H49: 0 | I49: 5 | J49: =I49 -> 5 | K49: 0 | L49: =J49-K49 -> 5 | M49: 0 | N49: =L49-M49 -> 5 | O49: 0 | P49: =N49-O49 -> 5 | Q49: 0 | R49: =P49-Q49 -> 5 | S49: 0 | T49: =R49-S49 -> 5 | U49: 0 | V49: =T49-U49 -> 5 | W49: 0 | X49: =V49-W49 -> 5 | Y49: 0 | Z49: =X49-Y49 -> 5 | AA49: 0 | AB49: =Z49-AA49 -> 5 | AC49: 0 | AD49: =AB49-AC49 -> 5 | AE49: 0 | AF49: =AD49-AE49 -> 5 | AG49: 0 | AH49: =AF49-AG49 -> 5 | AI49: 0 | AJ49: =AH49-AI49 -> 5 | AK49: 0 | AL49: =AJ49-AK49 -> 5 | AM49: 0 | AN49: =AL49-AM49 -> 5 | AO49: 0 | AP49: =AN49-AO49 -> 5 | AQ49: 0 | AR49: =AP49-AQ49 -> 5 | AS49: 0 | AT49: =AR49-AS49 -> 5 | AU49: 0 | AV49: =AT49-AU49 -> 5 | AW49: 3 | AX49: =AV49-AW49 -> 2 | AY49: 0 | AZ49: =AX49-AY49 -> 2 | BB49: =AY49+AW49+AU49+AS49+AQ49+AO49+AM49+AK49+AI49+AG49+AE49+AC49+AA49+Y49+W49+U49+S49+Q49+O49+M49+K49 -> 3 | BC49: =$BB49*D49 -> 0 | BD49: =BB49*F49 -> 3 | BE49: =BD49*G49 -> 0 | BF49: =$BB49*E49 -> 0 | BG49: =$BB49*H49 -> 0
C50: Ajout de l'affichage de la page dans le vue global | D50: 1 | E50: 0 | F50: 0 | G50: 0 | H50: 0 | I50: 2 | J50: =I50 -> 2 | K50: 0 | L50: =J50-K50 -> 2 | M50: 0 | N50: =L50-M50 -> 2 | O50: 0 | P50: =N50-O50 -> 2 | Q50: 0 | R50: =P50-Q50 -> 2 | S50: 0 | T50: =R50-S50 -> 2 | U50: 0 | V50: =T50-U50 -> 2 | W50: 0 | X50: =V50-W50 -> 2 | Y50: 0 | Z50: =X50-Y50 -> 2 | AA50: 0 | AB50: =Z50-AA50 -> 2 | AC50: 0 | AD50: =AB50-AC50 -> 2 | AE50: 0 | AF50: =AD50-AE50 -> 2 | AG50: 0 | AH50: =AF50-AG50 -> 2 | AI50: 0 | AJ50: =AH50-AI50 -> 2 | AK50: 0 | AL50: =AJ50-AK50 -> 2 | AM50: 0 | AN50: =AL50-AM50 -> 2 | AO50: 0 | AP50: =AN50-AO50 -> 2 | AQ50: 0 | AR50: =AP50-AQ50 -> 2 | AS50: 0 | AT50: =AR50-AS50 -> 2 | AU50: 0 | AV50: =AT50-AU50 -> 2 | AW50: 0 | AX50: =AV50-AW50 -> 2 | AY50: 2 | AZ50: =AX50-AY50 -> 0 | BB50: =AY50+AW50+AU50+AS50+AQ50+AO50+AM50+AK50+AI50+AG50+AE50+AC50+AA50+Y50+W50+U50+S50+Q50+O50+M50+K50 -> 2 | BC50: =$BB50*D50 -> 2 | BD50: =BB50*F50 -> 0 | BE50: =BD50*G50 -> 0 | BF50: =$BB50*E50 -> 0 | BG50: =$BB50*H50 -> 0
C51: Ajouter la fonctionnalité seulent la priorité des notifications(ex. examen - notification 3f par semaine, quiz - notifiaction 1-2f par semaine) | D51: 0 | E51: 0 | F51: 1 | G51: 0 | H51: 0 | I51: 5 | J51: =I51 -> 5 | K51: 0 | L51: =J51-K51 -> 5 | M51: 0 | N51: =L51-M51 -> 5 | O51: 0 | P51: =N51-O51 -> 5 | Q51: 0 | R51: =P51-Q51 -> 5 | S51: 0 | T51: =R51-S51 -> 5 | U51: 0 | V51: =T51-U51 -> 5 | W51: 0 | X51: =V51-W51 -> 5 | Y51: 0 | Z51: =X51-Y51 -> 5 | AA51: 0 | AB51: =Z51-AA51 -> 5 | AC51: 0 | AD51: =AB51-AC51 -> 5 | AE51: 0 | AF51: =AD51-AE51 -> 5 | AG51: 0 | AH51: =AF51-AG51 -> 5 | AI51: 0 | AJ51: =AH51-AI51 -> 5 | AK51: 0 | AL51: =AJ51-AK51 -> 5 | AM51: 0 | AN51: =AL51-AM51 -> 5 | AO51: 0 | AP51: =AN51-AO51 -> 5 | AQ51: 0 | AR51: =AP51-AQ51 -> 5 | AS51: 0 | AT51: =AR51-AS51 -> 5 | AU51: 0 | AV51: =AT51-AU51 -> 5 | AW51: 3 | AX51: =AV51-AW51 -> 2 | AY51: 2 | AZ51: =AX51-AY51 -> 0 | BB51: =AY51+AW51+AU51+AS51+AQ51+AO51+AM51+AK51+AI51+AG51+AE51+AC51+AA51+Y51+W51+U51+S51+Q51+O51+M51+K51 -> 5 | BC51: =$BB51*D51 -> 0 | BD51: =BB51*F51 -> 5 | BE51: =BD51*G51 -> 0 | BF51: =$BB51*E51 -> 0 | BG51: =$BB51*H51 -> 0
B52: 11 | C52: Gestion des notifications
C53: Ajouter la préférances des notifications - matin, soir,etc | D53: 0 | E53: 0 | F53: 1 | G53: 0 | H53: 0 | I53: 8 | J53: =I53 -> 8 | K53: 0 | L53: =J53-K53 -> 8 | M53: 0 | N53: =L53-M53 -> 8 | O53: 0 | P53: =N53-O53 -> 8 | Q53: 0 | R53: =P53-Q53 -> 8 | S53: 0 | T53: =R53-S53 -> 8 | U53: 0 | V53: =T53-U53 -> 8 | W53: 0 | X53: =V53-W53 -> 8 | Y53: 0 | Z53: =X53-Y53 -> 8 | AA53: 0 | AB53: =Z53-AA53 -> 8 | AC53: 0 | AD53: =AB53-AC53 -> 8 | AE53: 0 | AF53: =AD53-AE53 -> 8 | AG53: 0 | AH53: =AF53-AG53 -> 8 | AI53: 0 | AJ53: =AH53-AI53 -> 8 | AK53: 0 | AL53: =AJ53-AK53 -> 8 | AM53: 3 | AN53: =AL53-AM53 -> 5 | AO53: 3 | AP53: =AN53-AO53 -> 2 | AQ53: 0 | AR53: =AP53-AQ53 -> 2 | AS53: 0 | AT53: =AR53-AS53 -> 2 | AU53: 0 | AV53: =AT53-AU53 -> 2 | AW53: 0 | AX53: =AV53-AW53 -> 2 | AY53: 0 | AZ53: =AX53-AY53 -> 2 | BB53: =AY53+AW53+AU53+AS53+AQ53+AO53+AM53+AK53+AI53+AG53+AE53+AC53+AA53+Y53+W53+U53+S53+Q53+O53+M53+K53 -> 6 | BC53: =$BB53*D53 -> 0 | BD53: =BB53*F53 -> 6 | BE53: =BD53*G53 -> 0 | BF53: =$BB53*E53 -> 0 | BG53: =$BB53*H53 -> 0
C54: Ajouter la fréquences pour tous les notifications, peu importe la priorité | D54: 0 | E54: 0 | F54: 1 | G54: 0 | H54: 0 | I54: 3 | J54: 1 | K54: 0 | L54: =J54-K54 -> 1 | M54: 0 | N54: =L54-M54 -> 1 | O54: 0 | P54: =N54-O54 -> 1 | Q54: 0 | R54: =P54-Q54 -> 1 | S54: 0 | T54: =R54-S54 -> 1 | U54: 0 | V54: =T54-U54 -> 1 | W54: 0 | X54: =V54-W54 -> 1 | Y54: 0 | Z54: =X54-Y54 -> 1 | AA54: 0 | AB54: =Z54-AA54 -> 1 | AC54: 0 | AD54: =AB54-AC54 -> 1 | AE54: 0 | AF54: =AD54-AE54 -> 1 | AG54: 0 | AH54: =AF54-AG54 -> 1 | AI54: 0 | AJ54: =AH54-AI54 -> 1 | AK54: 0 | AL54: =AJ54-AK54 -> 1 | AM54: 0 | AN54: =AL54-AM54 -> 1 | AO54: 0 | AP54: =AN54-AO54 -> 1 | AQ54: 0 | AR54: =AP54-AQ54 -> 1 | AS54: 0 | AT54: =AR54-AS54 -> 1 | AU54: 0 | AV54: =AT54-AU54 -> 1 | AW54: 0 | AX54: =AV54-AW54 -> 1 | AY54: 0 | AZ54: =AX54-AY54 -> 1 | BB54: =AY54+AW54+AU54+AS54+AQ54+AO54+AM54+AK54+AI54+AG54+AE54+AC54+AA54+Y54+W54+U54+S54+Q54+O54+M54+K54 -> 0 | BC54: =$BB54*D54 -> 0 | BD54: =BB54*F54 -> 0 | BE54: =BD54*G54 -> 0 | BF54: =$BB54*E54 -> 0 | BG54: =$BB54*H54 -> 0
C55: Desactiver les notifications au besoin par utilisateur pour X temps | D55: 0 | E55: 0 | F55: 1 | G55: 0 | H55: 0 | I55: 3 | J55: =I55 -> 3 | K55: 0 | L55: =J55-K55 -> 3 | M55: 0 | N55: =L55-M55 -> 3 | O55: 0 | P55: =N55-O55 -> 3 | Q55: 0 | R55: =P55-Q55 -> 3 | S55: 0 | T55: =R55-S55 -> 3 | U55: 0 | V55: =T55-U55 -> 3 | W55: 0 | X55: =V55-W55 -> 3 | Y55: 0 | Z55: =X55-Y55 -> 3 | AA55: 0 | AB55: =Z55-AA55 -> 3 | AC55: 0 | AD55: =AB55-AC55 -> 3 | AE55: 0 | AF55: =AD55-AE55 -> 3 | AG55: 0 | AH55: =AF55-AG55 -> 3 | AI55: 0 | AJ55: =AH55-AI55 -> 3 | AK55: 0 | AL55: =AJ55-AK55 -> 3 | AM55: 0 | AN55: =AL55-AM55 -> 3 | AO55: 0 | AP55: =AN55-AO55 -> 3 | AQ55: 0 | AR55: =AP55-AQ55 -> 3 | AS55: 0 | AT55: =AR55-AS55 -> 3 | AU55: 0 | AV55: =AT55-AU55 -> 3 | AW55: 0 | AX55: =AV55-AW55 -> 3 | AY55: 0 | AZ55: =AX55-AY55 -> 3 | BB55: =AY55+AW55+AU55+AS55+AQ55+AO55+AM55+AK55+AI55+AG55+AE55+AC55+AA55+Y55+W55+U55+S55+Q55+O55+M55+K55 -> 0 | BC55: =$BB55*D55 -> 0 | BD55: =BB55*F55 -> 0 | BE55: =BD55*G55 -> 0 | BF55: =$BB55*E55 -> 0 | BG55: =$BB55*H55 -> 0
A56: SPRINT 2 | B56: 51 | C56: Correction à apporter - création de possibilité de réinitialiser le mot de passe
C57: Creation du bouton - mot de passe oublie | D57: 1 | E57: 0 | F57: 0 | G57: 0 | H57: 0 | I57: 2 | J57: =I57 -> 2 | K57: 0 | L57: =J57-K57 -> 2 | M57: 0 | N57: =L57-M57 -> 2 | O57: 0 | P57: =N57-O57 -> 2 | Q57: 0 | R57: =P57-Q57 -> 2 | S57: 0 | T57: =R57-S57 -> 2 | U57: 0 | V57: =T57-U57 -> 2 | W57: 2 | X57: =V57-W57 -> 0 | Y57: 0 | Z57: =X57-Y57 -> 0 | AA57: 0 | AB57: =Z57-AA57 -> 0 | AC57: 0 | AD57: =AB57-AC57 -> 0 | AE57: 0 | AF57: =AD57-AE57 -> 0 | AG57: 0 | AH57: =AF57-AG57 -> 0 | AI57: 0 | AJ57: =AH57-AI57 -> 0 | AK57: 0 | AL57: =AJ57-AK57 -> 0 | AM57: 0 | AN57: =AL57-AM57 -> 0 | AO57: 0 | AP57: =AN57-AO57 -> 0 | AQ57: 0 | AR57: =AP57-AQ57 -> 0 | AS57: 0 | AT57: =AR57-AS57 -> 0 | AU57: 0 | AV57: =AT57-AU57 -> 0 | AW57: 0 | AX57: =AV57-AW57 -> 0 | AY57: 0 | AZ57: =AX57-AY57 -> 0 | BB57: =AY57+AW57+AU57+AS57+AQ57+AO57+AM57+AK57+AI57+AG57+AE57+AC57+AA57+Y57+W57+U57+S57+Q57+O57+M57+K57 -> 2 | BC57: =$BB57*D57 -> 2 | BD57: =BC57*F57 -> 0 | BE57: =BD57*G57 -> 0 | BF57: =$BB57*E57 -> 0 | BG57: =$BB57*H57 -> 0
C58: Renvoyer le mot de passe temporaire - courriel ou # télé. | D58: 1 | E58: 0 | F58: 0 | G58: 0 | H58: 0 | I58: 2 | J58: =I58 -> 2 | L58: =J58-K58 -> 2 | N58: =L58-M58 -> 2 | P58: =N58-O58 -> 2 | R58: =P58-Q58 -> 2 | T58: =R58-S58 -> 2 | V58: =T58-U58 -> 2 | X58: =V58-W58 -> 2 | Z58: =X58-Y58 -> 2 | AB58: =Z58-AA58 -> 2 | AD58: =AB58-AC58 -> 2 | AF58: =AD58-AE58 -> 2 | AH58: =AF58-AG58 -> 2 | AJ58: =AH58-AI58 -> 2 | AL58: =AJ58-AK58 -> 2 | AN58: =AL58-AM58 -> 2 | AP58: =AN58-AO58 -> 2 | AR58: =AP58-AQ58 -> 2 | AT58: =AR58-AS58 -> 2 | AV58: =AT58-AU58 -> 2 | AX58: =AV58-AW58 -> 2 | AZ58: =AX58-AY58 -> 2 | BB58: =AY58+AW58+AU58+AS58+AQ58+AO58+AM58+AK58+AI58+AG58+AE58+AC58+AA58+Y58+W58+U58+S58+Q58+O58+M58+K58 -> 0 | BC58: =$BB58*D58 -> 0 | BD58: =BC58*F58 -> 0 | BE58: =BD58*G58 -> 0 | BF58: =$BB58*E58 -> 0 | BG58: =$BB58*H58 -> 0
B59: 52 | C59: Correction du profil d'utilisateur
C60: Creation de la page d'utilisateur | D60: 1 | E60: 0 | F60: 0 | G60: 0 | H60: 0 | I60: 6 | J60: =I60 -> 6 | L60: =J60-K60 -> 6 | N60: =L60-M60 -> 6 | P60: =N60-O60 -> 6 | R60: =P60-Q60 -> 6 | T60: =R60-S60 -> 6 | V60: =T60-U60 -> 6 | X60: =V60-W60 -> 6 | Z60: =X60-Y60 -> 6 | AB60: =Z60-AA60 -> 6 | AD60: =AB60-AC60 -> 6 | AF60: =AD60-AE60 -> 6 | AH60: =AF60-AG60 -> 6 | AJ60: =AH60-AI60 -> 6 | AL60: =AJ60-AK60 -> 6 | AN60: =AL60-AM60 -> 6 | AP60: =AN60-AO60 -> 6 | AR60: =AP60-AQ60 -> 6 | AT60: =AR60-AS60 -> 6 | AV60: =AT60-AU60 -> 6 | AX60: =AV60-AW60 -> 6 | AZ60: =AX60-AY60 -> 6 | BB60: =AY60+AW60+AU60+AS60+AQ60+AO60+AM60+AK60+AI60+AG60+AE60+AC60+AA60+Y60+W60+U60+S60+Q60+O60+M60+K60 -> 0 | BC60: =$BB60*D60 -> 0 | BD60: =BC60*F60 -> 0 | BE60: =BD60*G60 -> 0 | BF60: =$BB60*E60 -> 0 | BG60: =$BB60*H60 -> 0
C61: Ajouter dashboard et les modifications possibles | D61: 1 | E61: 0 | F61: 0 | G61: 0 | H61: 0 | I61: 4 | J61: =I61 -> 4 | L61: =J61-K61 -> 4 | N61: =L61-M61 -> 4 | P61: =N61-O61 -> 4 | R61: =P61-Q61 -> 4 | T61: =R61-S61 -> 4 | V61: =T61-U61 -> 4 | X61: =V61-W61 -> 4 | Z61: =X61-Y61 -> 4 | AB61: =Z61-AA61 -> 4 | AD61: =AB61-AC61 -> 4 | AF61: =AD61-AE61 -> 4 | AH61: =AF61-AG61 -> 4 | AJ61: =AH61-AI61 -> 4 | AL61: =AJ61-AK61 -> 4 | AN61: =AL61-AM61 -> 4 | AP61: =AN61-AO61 -> 4 | AR61: =AP61-AQ61 -> 4 | AT61: =AR61-AS61 -> 4 | AV61: =AT61-AU61 -> 4 | AX61: =AV61-AW61 -> 4 | AZ61: =AX61-AY61 -> 4 | BB61: =AY61+AW61+AU61+AS61+AQ61+AO61+AM61+AK61+AI61+AG61+AE61+AC61+AA61+Y61+W61+U61+S61+Q61+O61+M61+K61 -> 0 | BC61: =$BB61*D61 -> 0 | BD61: =BC61*F61 -> 0 | BE61: =BD61*G61 -> 0 | BF61: =$BB61*E61 -> 0 | BG61: =$BB61*H61 -> 0
B62: 53 | C62: Gestion des cours : Bonification gestion du seuil du passage - calcul automatique min requis pour passer le cours selon les notes concernées déjà obtenues
C63: US1 Saisie des évaluations & pondérations | D63: 0 | E63: 0 | F63: 0 | G63: 0 | H63: 1 | I63: 2 | J63: =I63 -> 2 | L63: =J63-K63 -> 2 | N63: =L63-M63 -> 2 | P63: =N63-O63 -> 2 | R63: =P63-Q63 -> 2 | T63: =R63-S63 -> 2 | V63: =T63-U63 -> 2 | X63: =V63-W63 -> 2 | Z63: =X63-Y63 -> 2 | AB63: =Z63-AA63 -> 2 | AD63: =AB63-AC63 -> 2 | AF63: =AD63-AE63 -> 2 | AH63: =AF63-AG63 -> 2 | AJ63: =AH63-AI63 -> 2 | AL63: =AJ63-AK63 -> 2 | AN63: =AL63-AM63 -> 2 | AP63: =AN63-AO63 -> 2 | AR63: =AP63-AQ63 -> 2 | AT63: =AR63-AS63 -> 2 | AV63: =AT63-AU63 -> 2 | AX63: =AV63-AW63 -> 2 | AZ63: =AX63-AY63 -> 2 | BB63: =AY63+AW63+AU63+AS63+AQ63+AO63+AM63+AK63+AI63+AG63+AE63+AC63+AA63+Y63+W63+U63+S63+Q63+O63+M63+K63 -> 0 | BC63: =$BB63*D63 -> 0 | BD63: =BC63*F63 -> 0 | BE63: =BD63*G63 -> 0 | BF63: =$BB63*E63 -> 0 | BG63: =$BB63*H63 -> 0
C64: US2 Saisie des notes obtenues | D64: 0 | E64: 0 | F64: 0 | G64: 0 | H64: 1 | I64: 2 | J64: =I64 -> 2 | L64: =J64-K64 -> 2 | N64: =L64-M64 -> 2 | P64: =N64-O64 -> 2 | R64: =P64-Q64 -> 2 | T64: =R64-S64 -> 2 | V64: =T64-U64 -> 2 | X64: =V64-W64 -> 2 | Z64: =X64-Y64 -> 2 | AB64: =Z64-AA64 -> 2 | AD64: =AB64-AC64 -> 2 | AF64: =AD64-AE64 -> 2 | AH64: =AF64-AG64 -> 2 | AJ64: =AH64-AI64 -> 2 | AL64: =AJ64-AK64 -> 2 | AN64: =AL64-AM64 -> 2 | AP64: =AN64-AO64 -> 2 | AR64: =AP64-AQ64 -> 2 | AT64: =AR64-AS64 -> 2 | AV64: =AT64-AU64 -> 2 | AX64: =AV64-AW64 -> 2 | AZ64: =AX64-AY64 -> 2 | BB64: =AY64+AW64+AU64+AS64+AQ64+AO64+AM64+AK64+AI64+AG64+AE64+AC64+AA64+Y64+W64+U64+S64+Q64+O64+M64+K64 -> 0 | BC64: =$BB64*D64 -> 0 | BD64: =BC64*F64 -> 0 | BE64: =BD64*G64 -> 0 | BF64: =$BB64*E64 -> 0 | BG64: =$BB64*H64 -> 0
C65: US3 Calcul de moyenne pondérée actuelle | D65: 0 | E65: 0 | F65: 0 | G65: 0 | H65: 1 | I65: 2 | J65: =I65 -> 2 | L65: =J65-K65 -> 2 | N65: =L65-M65 -> 2 | P65: =N65-O65 -> 2 | R65: =P65-Q65 -> 2 | T65: =R65-S65 -> 2 | V65: =T65-U65 -> 2 | X65: =V65-W65 -> 2 | Z65: =X65-Y65 -> 2 | AB65: =Z65-AA65 -> 2 | AD65: =AB65-AC65 -> 2 | AF65: =AD65-AE65 -> 2 | AH65: =AF65-AG65 -> 2 | AJ65: =AH65-AI65 -> 2 | AL65: =AJ65-AK65 -> 2 | AN65: =AL65-AM65 -> 2 | AP65: =AN65-AO65 -> 2 | AR65: =AP65-AQ65 -> 2 | AT65: =AR65-AS65 -> 2 | AV65: =AT65-AU65 -> 2 | AX65: =AV65-AW65 -> 2 | AZ65: =AX65-AY65 -> 2 | BB65: =AY65+AW65+AU65+AS65+AQ65+AO65+AM65+AK65+AI65+AG65+AE65+AC65+AA65+Y65+W65+U65+S65+Q65+O65+M65+K65 -> 0 | BC65: =$BB65*D65 -> 0 | BD65: =BC65*F65 -> 0 | BE65: =BD65*G65 -> 0 | BF65: =$BB65*E65 -> 0 | BG65: =$BB65*H65 -> 0
C66: US4 Calcul du minimum à obtenir pour atteindre le seuil | D66: 0 | E66: 0 | F66: 0 | G66: 0 | H66: 1 | I66: 4 | J66: =I66 -> 4 | L66: =J66-K66 -> 4 | N66: =L66-M66 -> 4 | P66: =N66-O66 -> 4 | R66: =P66-Q66 -> 4 | T66: =R66-S66 -> 4 | V66: =T66-U66 -> 4 | X66: =V66-W66 -> 4 | Z66: =X66-Y66 -> 4 | AB66: =Z66-AA66 -> 4 | AD66: =AB66-AC66 -> 4 | AF66: =AD66-AE66 -> 4 | AH66: =AF66-AG66 -> 4 | AJ66: =AH66-AI66 -> 4 | AL66: =AJ66-AK66 -> 4 | AN66: =AL66-AM66 -> 4 | AP66: =AN66-AO66 -> 4 | AR66: =AP66-AQ66 -> 4 | AT66: =AR66-AS66 -> 4 | AV66: =AT66-AU66 -> 4 | AX66: =AV66-AW66 -> 4 | AZ66: =AX66-AY66 -> 4 | BB66: =AY66+AW66+AU66+AS66+AQ66+AO66+AM66+AK66+AI66+AG66+AE66+AC66+AA66+Y66+W66+U66+S66+Q66+O66+M66+K66 -> 0 | BC66: =$BB66*D66 -> 0 | BD66: =BC66*F66 -> 0 | BE66: =BD66*G66 -> 0 | BF66: =$BB66*E66 -> 0 | BG66: =$BB66*H66 -> 0
B67: 54 | C67: Correction de la vue global - calendrier correction dans le Sprint 2
C68: Implémentation de la vue quotidienne | D68: 0 | E68: 1 | F68: 0 | G68: 0 | H68: 0 | I68: 9 | J68: =I68 -> 9 | K68: 0 | L68: =J68-K68 -> 9 | M68: 0 | N68: =L68-M68 -> 9 | O68: 0 | P68: =N68-O68 -> 9 | Q68: 0 | R68: =P68-Q68 -> 9 | S68: 0 | T68: =R68-S68 -> 9 | U68: 0 | V68: =T68-U68 -> 9 | W68: 0 | X68: =V68-W68 -> 9 | Y68: 0 | Z68: =X68-Y68 -> 9 | AA68: 3 | AB68: =Z68-AA68 -> 6 | AC68: 2 | AD68: =AB68-AC68 -> 4 | AE68: 0 | AF68: =AD68-AE68 -> 4 | AG68: 0 | AH68: =AF68-AG68 -> 4 | AI68: 3 | AJ68: 0 | AL68: =AJ68-AK68 -> 0 | AN68: =AL68-AM68 -> 0 | AP68: =AN68-AO68 -> 0 | AR68: =AP68-AQ68 -> 0 | AT68: =AR68-AS68 -> 0 | AV68: =AT68-AU68 -> 0 | AX68: =AV68-AW68 -> 0 | AZ68: =AX68-AY68 -> 0 | BB68: =AY68+AW68+AU68+AS68+AQ68+AO68+AM68+AK68+AI68+AG68+AE68+AC68+AA68+Y68+W68+U68+S68+Q68+O68+M68+K68 -> 8 | BC68: =$BB68*D68 -> 0 | BD68: =BC68*F68 -> 0 | BE68: =BD68*G68 -> 0 | BF68: =$BB68*E68 -> 8 | BG68: =$BB68*H68 -> 0
B69: 12 | C69: Calcul de priorité d'évènement basique (IA v1) | D69: 1
C70: Identifier les paramètres nécessaires et définir la formule du calcul | D70: =D69 -> 1 | E70: 0 | F70: 0 | G70: 0 | H70: 0 | I70: 2 | J70: =I70 -> 2 | K70: 0 | L70: =J70-K70 -> 2 | M70: 0 | N70: =L70-M70 -> 2 | O70: 0 | P70: =N70-O70 -> 2 | Q70: 0 | R70: =P70-Q70 -> 2 | S70: 0 | T70: =R70-S70 -> 2 | U70: 2 | V70: =T70-U70 -> 0 | W70: 0 | X70: =V70-W70 -> 0 | Y70: 0 | Z70: =X70-Y70 -> 0 | AA70: 0 | AB70: =Z70-AA70 -> 0 | AC70: 0 | AD70: =AB70-AC70 -> 0 | AE70: 0 | AF70: =AD70-AE70 -> 0 | AG70: 0 | AH70: =AF70-AG70 -> 0 | AI70: 0 | AJ70: =AH70-AI70 -> 0 | AK70: 0 | AL70: =AJ70-AK70 -> 0 | AM70: 0 | AN70: =AL70-AM70 -> 0 | AO70: 0 | AP70: =AN70-AO70 -> 0 | AQ70: 0 | AR70: =AP70-AQ70 -> 0 | AS70: 0 | AT70: =AR70-AS70 -> 0 | AU70: 0 | AV70: =AT70-AU70 -> 0 | AW70: 0 | AX70: =AV70-AW70 -> 0 | AY70: 0 | AZ70: =AX70-AY70 -> 0 | BB70: =AY70+AW70+AU70+AS70+AQ70+AO70+AM70+AK70+AI70+AG70+AE70+AC70+AA70+Y70+W70+U70+S70+Q70+O70+M70+K70 -> 2 | BC70: =$BB70*D70 -> 2 | BD70: =BC70*F70 -> 0 | BE70: =BD70*G70 -> 0 | BF70: =$BB70*E70 -> 0 | BG70: =$BB70*H70 -> 0
C71: Effectuer l'implémentation du calcul | D71: =D69 -> 1 | E71: 0 | F71: 0 | G71: 0 | H71: 0 | I71: 4 | J71: =I71 -> 4 | K71: 0 | L71: =J71-K71 -> 4 | M71: 0 | N71: =L71-M71 -> 4 | O71: 0 | P71: =N71-O71 -> 4 | Q71: 0 | R71: =P71-Q71 -> 4 | S71: 0 | T71: =R71-S71 -> 4 | U71: 0 | V71: =T71-U71 -> 4 | W71: 2 | X71: =V71-W71 -> 2 | Y71: 0 | Z71: =X71-Y71 -> 2 | AA71: 2 | AB71: 3 | AC71: 1 | AD71: =AB71-AC71 -> 2 | AE71: 0 | AF71: =AD71-AE71 -> 2 | AG71: 2 | AH71: =AF71-AG71 -> 0 | AI71: 0 | AJ71: =AH71-AI71 -> 0 | AK71: 0 | AL71: =AJ71-AK71 -> 0 | AM71: 0 | AN71: =AL71-AM71 -> 0 | AO71: 0 | AP71: =AN71-AO71 -> 0 | AQ71: 0 | AR71: =AP71-AQ71 -> 0 | AS71: 0 | AT71: =AR71-AS71 -> 0 | AU71: 0 | AV71: =AT71-AU71 -> 0 | AW71: 0 | AX71: =AV71-AW71 -> 0 | AY71: 0 | AZ71: =AX71-AY71 -> 0 | BB71: =AY71+AW71+AU71+AS71+AQ71+AO71+AM71+AK71+AI71+AG71+AE71+AC71+AA71+Y71+W71+U71+S71+Q71+O71+M71+K71 -> 7 | BC71: =$BB71*D71 -> 7 | BD71: =BC71*F71 -> 0 | BE71: =BD71*G71 -> 0 | BF71: =$BB71*E71 -> 0 | BG71: =$BB71*H71 -> 0
C72: Intégration au système | D72: =D70 -> 1 | E72: 0 | F72: 0 | G72: 0 | H72: 0 | I72: 10 | J72: =I72 -> 10 | K72: 0 | L72: =J72-K72 -> 10 | M72: 0 | N72: =L72-M72 -> 10 | O72: 0 | P72: =N72-O72 -> 10 | Q72: 0 | R72: =P72-Q72 -> 10 | S72: 0 | T72: =R72-S72 -> 10 | U72: 0 | V72: =T72-U72 -> 10 | W72: 0 | X72: =V72-W72 -> 10 | Y72: 4 | Z72: =X72-Y72 -> 6 | AA72: 0 | AB72: =Z72-AA72 -> 6 | AC72: 4 | AD72: =AB72-AC72 -> 2 | AE72: 0 | AF72: 3 | AG72: 3 | AH72: 1 | AI72: 1 | AJ72: =AH72-AI72 -> 0 | AK72: 0 | AL72: =AJ72-AK72 -> 0 | AM72: 0 | AN72: =AL72-AM72 -> 0 | AO72: 0 | AP72: =AN72-AO72 -> 0 | AQ72: 0 | AR72: =AP72-AQ72 -> 0 | AS72: 0 | AT72: =AR72-AS72 -> 0 | AU72: 0 | AV72: =AT72-AU72 -> 0 | AW72: 0 | AX72: =AV72-AW72 -> 0 | AY72: 0 | AZ72: =AX72-AY72 -> 0 | BB72: =AY72+AW72+AU72+AS72+AQ72+AO72+AM72+AK72+AI72+AG72+AE72+AC72+AA72+Y72+W72+U72+S72+Q72+O72+M72+K72 -> 12 | BC72: =$BB72*D72 -> 12 | BD72: =BC72*F72 -> 0 | BE72: =BD72*G72 -> 0 | BF72: =$BB72*E72 -> 0 | BG72: =$BB72*H72 -> 0
C73: Validation et test | D73: =D71 -> 1 | E73: =E71 -> 0 | F73: 0 | G73: 0 | H73: 0 | I73: 2 | J73: =I73 -> 2 | K73: 0 | L73: =J73-K73 -> 2 | M73: 0 | N73: =L73-M73 -> 2 | O73: 0 | P73: =N73-O73 -> 2 | Q73: 0 | R73: =P73-Q73 -> 2 | S73: 0 | T73: =R73-S73 -> 2 | U73: 0 | V73: 2 | W73: 0 | X73: =V73-W73 -> 2 | Y73: 0 | Z73: =X73-Y73 -> 2 | AA73: 0 | AB73: =Z73-AA73 -> 2 | AC73: 0 | AD73: =AB73-AC73 -> 2 | AE73: 0 | AF73: =AD73-AE73 -> 2 | AG73: 2 | AH73: =AF73-AG73 -> 0 | AI73: 0 | AJ73: 2 | AK73: 2 | AL73: =AJ73-AK73 -> 0 | AM73: 0 | AN73: =AL73-AM73 -> 0 | AO73: 0 | AP73: =AN73-AO73 -> 0 | AQ73: 0 | AR73: =AP73-AQ73 -> 0 | AS73: 0 | AT73: =AR73-AS73 -> 0 | AU73: 0 | AV73: =AT73-AU73 -> 0 | AW73: 0 | AX73: =AV73-AW73 -> 0 | AY73: 0 | AZ73: =AX73-AY73 -> 0 | BB73: =AY73+AW73+AU73+AS73+AQ73+AO73+AM73+AK73+AI73+AG73+AE73+AC73+AA73+Y73+W73+U73+S73+Q73+O73+M73+K73 -> 4 | BC73: =$BB73*D73 -> 4 | BD73: =BC73*F73 -> 0 | BE73: =BD73*G73 -> 0 | BF73: =$BB73*E73 -> 0 | BG73: =$BB73*H73 -> 0
C74: Affichage - ajouter la visualisation de l'indice de priorité dans l'interace utilisateur | D74: =D72 -> 1 | E74: 0 | F74: 0 | G74: 0 | H74: 0 | I74: 2 | J74: =I74 -> 2 | K74: 0 | L74: =J74-K74 -> 2 | M74: 0 | N74: =L74-M74 -> 2 | O74: 0 | P74: =N74-O74 -> 2 | Q74: 0 | R74: =P74-Q74 -> 2 | S74: 0 | T74: =R74-S74 -> 2 | U74: 0 | V74: 2 | W74: 0 | X74: =V74-W74 -> 2 | Y74: 0 | Z74: =X74-Y74 -> 2 | AA74: 0 | AB74: =Z74-AA74 -> 2 | AC74: 0 | AD74: =AB74-AC74 -> 2 | AE74: 2 | AF74: =AD74-AE74 -> 0 | AG74: 0 | AH74: 3 | AI74: 3 | AJ74: =AH74-AI74 -> 0 | AK74: 0 | AL74: =AJ74-AK74 -> 0 | AM74: 0 | AN74: =AL74-AM74 -> 0 | AO74: 0 | AP74: =AN74-AO74 -> 0 | AQ74: 0 | AR74: =AP74-AQ74 -> 0 | AS74: 0 | AT74: =AR74-AS74 -> 0 | AU74: 0 | AV74: =AT74-AU74 -> 0 | AW74: 0 | AX74: =AV74-AW74 -> 0 | AY74: 0 | AZ74: =AX74-AY74 -> 0 | BB74: =AY74+AW74+AU74+AS74+AQ74+AO74+AM74+AK74+AI74+AG74+AE74+AC74+AA74+Y74+W74+U74+S74+Q74+O74+M74+K74 -> 5 | BC74: =$BB74*D74 -> 5 | BD74: =BC74*F74 -> 0 | BE74: =BD74*G74 -> 0 | BF74: =$BB74*E74 -> 0 | BG74: =$BB74*H74 -> 0
B75: 13 | C75: Barre de progression | D75: 1
C76: Identifier les éléments mesurant l'avancement | D76: =D75 -> 1 | E76: 0 | F76: 0 | G76: 0 | H76: 0 | I76: 2 | J76: =I76 -> 2 | L76: =J76-K76 -> 2 | N76: =L76-M76 -> 2 | P76: =N76-O76 -> 2 | R76: =P76-Q76 -> 2 | T76: =R76-S76 -> 2 | V76: =T76-U76 -> 2 | X76: =V76-W76 -> 2 | Z76: =X76-Y76 -> 2 | AB76: =Z76-AA76 -> 2 | AD76: =AB76-AC76 -> 2 | AF76: =AD76-AE76 -> 2 | AH76: =AF76-AG76 -> 2 | AJ76: =AH76-AI76 -> 2 | AL76: =AJ76-AK76 -> 2 | AN76: =AL76-AM76 -> 2 | AP76: =AN76-AO76 -> 2 | AR76: =AP76-AQ76 -> 2 | AT76: =AR76-AS76 -> 2 | AV76: =AT76-AU76 -> 2 | AX76: =AV76-AW76 -> 2 | AZ76: =AX76-AY76 -> 2 | BB76: =AY76+AW76+AU76+AS76+AQ76+AO76+AM76+AK76+AI76+AG76+AE76+AC76+AA76+Y76+W76+U76+S76+Q76+O76+M76+K76 -> 0 | BC76: =$BB76*D76 -> 0 | BD76: =BC76*F76 -> 0 | BE76: =BD76*G76 -> 0 | BF76: =$BB76*E76 -> 0 | BG76: =$BB76*H76 -> 0
C77: Calcul du pourcentage d'avancement | D77: =D76 -> 1 | E77: 0 | F77: 0 | G77: 0 | H77: 0 | I77: 2 | J77: =I77 -> 2 | L77: =J77-K77 -> 2 | N77: =L77-M77 -> 2 | P77: =N77-O77 -> 2 | R77: =P77-Q77 -> 2 | T77: =R77-S77 -> 2 | V77: =T77-U77 -> 2 | X77: =V77-W77 -> 2 | Z77: =X77-Y77 -> 2 | AB77: =Z77-AA77 -> 2 | AD77: =AB77-AC77 -> 2 | AF77: =AD77-AE77 -> 2 | AH77: =AF77-AG77 -> 2 | AJ77: =AH77-AI77 -> 2 | AL77: =AJ77-AK77 -> 2 | AN77: =AL77-AM77 -> 2 | AP77: =AN77-AO77 -> 2 | AR77: =AP77-AQ77 -> 2 | AT77: =AR77-AS77 -> 2 | AV77: =AT77-AU77 -> 2 | AX77: =AV77-AW77 -> 2 | AZ77: =AX77-AY77 -> 2 | BB77: =AY77+AW77+AU77+AS77+AQ77+AO77+AM77+AK77+AI77+AG77+AE77+AC77+AA77+Y77+W77+U77+S77+Q77+O77+M77+K77 -> 0 | BC77: =$BB77*D77 -> 0 | BD77: =BC77*F77 -> 0 | BE77: =BD77*G77 -> 0 | BF77: =$BB77*E77 -> 0 | BG77: =$BB77*H77 -> 0
C78: Conception de la barre de progression | D78: =D77 -> 1 | E78: 0 | F78: 0 | G78: 0 | H78: 0 | I78: 8 | J78: =I78 -> 8 | L78: =J78-K78 -> 8 | N78: =L78-M78 -> 8 | P78: =N78-O78 -> 8 | R78: =P78-Q78 -> 8 | T78: =R78-S78 -> 8 | V78: =T78-U78 -> 8 | X78: =V78-W78 -> 8 | Z78: =X78-Y78 -> 8 | AB78: =Z78-AA78 -> 8 | AD78: =AB78-AC78 -> 8 | AF78: =AD78-AE78 -> 8 | AH78: =AF78-AG78 -> 8 | AJ78: =AH78-AI78 -> 8 | AL78: =AJ78-AK78 -> 8 | AN78: =AL78-AM78 -> 8 | AP78: =AN78-AO78 -> 8 | AR78: =AP78-AQ78 -> 8 | AT78: =AR78-AS78 -> 8 | AV78: =AT78-AU78 -> 8 | AX78: =AV78-AW78 -> 8 | AZ78: =AX78-AY78 -> 8 | BB78: =AY78+AW78+AU78+AS78+AQ78+AO78+AM78+AK78+AI78+AG78+AE78+AC78+AA78+Y78+W78+U78+S78+Q78+O78+M78+K78 -> 0 | BC78: =$BB78*D78 -> 0 | BD78: =BC78*F78 -> 0 | BE78: =BD78*G78 -> 0 | BF78: =$BB78*E78 -> 0 | BG78: =$BB78*H78 -> 0
C79: Intégration dynamique | D79: =D78 -> 1 | E79: 0 | F79: 0 | G79: 0 | H79: 0 | I79: 6 | J79: =I79 -> 6 | L79: =J79-K79 -> 6 | N79: =L79-M79 -> 6 | P79: =N79-O79 -> 6 | R79: =P79-Q79 -> 6 | T79: =R79-S79 -> 6 | V79: =T79-U79 -> 6 | X79: =V79-W79 -> 6 | Z79: =X79-Y79 -> 6 | AB79: =Z79-AA79 -> 6 | AD79: =AB79-AC79 -> 6 | AF79: =AD79-AE79 -> 6 | AH79: =AF79-AG79 -> 6 | AJ79: =AH79-AI79 -> 6 | AL79: =AJ79-AK79 -> 6 | AN79: =AL79-AM79 -> 6 | AP79: =AN79-AO79 -> 6 | AR79: =AP79-AQ79 -> 6 | AT79: =AR79-AS79 -> 6 | AV79: =AT79-AU79 -> 6 | AX79: =AV79-AW79 -> 6 | AZ79: =AX79-AY79 -> 6 | BB79: =AY79+AW79+AU79+AS79+AQ79+AO79+AM79+AK79+AI79+AG79+AE79+AC79+AA79+Y79+W79+U79+S79+Q79+O79+M79+K79 -> 0 | BC79: =$BB79*D79 -> 0 | BD79: =BC79*F79 -> 0 | BE79: =BD79*G79 -> 0 | BF79: =$BB79*E79 -> 0 | BG79: =$BB79*H79 -> 0
C80: Test et validation : exactitude du pourcentage et le rendu visuel sur différents états | D80: =D79 -> 1 | E80: 0 | F80: 0 | G80: 0 | H80: 0 | I80: 4 | J80: =I80 -> 4 | L80: =J80-K80 -> 4 | N80: =L80-M80 -> 4 | P80: =N80-O80 -> 4 | R80: =P80-Q80 -> 4 | T80: =R80-S80 -> 4 | V80: =T80-U80 -> 4 | X80: =V80-W80 -> 4 | Z80: =X80-Y80 -> 4 | AB80: =Z80-AA80 -> 4 | AD80: =AB80-AC80 -> 4 | AF80: =AD80-AE80 -> 4 | AH80: =AF80-AG80 -> 4 | AJ80: =AH80-AI80 -> 4 | AL80: =AJ80-AK80 -> 4 | AN80: =AL80-AM80 -> 4 | AP80: =AN80-AO80 -> 4 | AR80: =AP80-AQ80 -> 4 | AT80: =AR80-AS80 -> 4 | AV80: =AT80-AU80 -> 4 | AX80: =AV80-AW80 -> 4 | AZ80: =AX80-AY80 -> 4 | BB80: =AY80+AW80+AU80+AS80+AQ80+AO80+AM80+AK80+AI80+AG80+AE80+AC80+AA80+Y80+W80+U80+S80+Q80+O80+M80+K80 -> 0 | BC80: =$BB80*D80 -> 0 | BD80: =BC80*F80 -> 0 | BE80: =BD80*G80 -> 0 | BF80: =$BB80*E80 -> 0 | BG80: =$BB80*H80 -> 0
B81: 14 | C81: Placement automatique de blocs d’étude. US : En tant qu’étudiant, je peux générer automatiquement des blocs d’étude (25/45/60/90 min) dans mes créneaux libres aujourd’hui, sans écraser mes événements existants
C82: Algorithme de placement minimal : entrées : durée, fenêtre jour (start/end), événements existants sortie: premier créneau libre valide régle : pas d'overlap | D82: 0 | E82: 0 | F82: 0 | G82: 0 | H82: 1 | I82: 30 | J82: =I82 -> 30 | K82: 0 | L82: =J82-K82 -> 30 | M82: 0 | N82: =L82-M82 -> 30 | O82: 0 | P82: =N82-O82 -> 30 | Q82: 0 | R82: =P82-Q82 -> 30 | S82: 0 | T82: =R82-S82 -> 30 | U82: 4 | V82: =T82-U82 -> 26 | W82: 0 | X82: =V82-W82 -> 26 | Y82: 3 | Z82: =X82-Y82 -> 23 | AA82: 4 | AB82: =Z82-AA82 -> 19 | AC82: 1 | AD82: =AB82-AC82 -> 18 | AE82: 2 | AF82: =AD82-AE82 -> 16 | AG82: 0 | AH82: =AF82-AG82 -> 16 | AI82: 2 | AJ82: =AH82-AI82 -> 14 | AK82: 1 | AL82: =AJ82-AK82 -> 13 | AM82: 1 | AN82: =AL82-AM82 -> 12 | AO82: 0 | AP82: =AN82-AO82 -> 12 | AQ82: 0 | AR82: =AP82-AQ82 -> 12 | AS82: 0 | AT82: =AR82-AS82 -> 12 | AU82: 6 | AV82: =AT82-AU82 -> 6 | AW82: 4 | AX82: 0 | AY82: 0 | AZ82: =AX82-AY82 -> 0 | BB82: =AY82+AW82+AU82+AS82+AQ82+AO82+AM82+AK82+AI82+AG82+AE82+AC82+AA82+Y82+W82+U82+S82+Q82+O82+M82+K82 -> 28 | BC82: =$BB82*D82 -> 0 | BD82: =BC82*F82 -> 0 | BE82: =BD82*G82 -> 0 | BF82: =$BB82*E82 -> 0 | BG82: =$BB82*H82 -> 28
C83: Action “Générer un bloc” : Bouton + select durée (25/45/60/90), message succès/échec, Undo (supprime le dernier bloc auto) | D83: 0 | E83: 0 | F83: 0 | G83: 0 | H83: 1 | I83: 10 | J83: =I83 -> 10 | K83: 0 | L83: =J83-K83 -> 10 | M83: 0 | N83: =L83-M83 -> 10 | O83: 0 | P83: =N83-O83 -> 10 | Q83: 0 | R83: =P83-Q83 -> 10 | S83: 0 | T83: =R83-S83 -> 10 | U83: 0 | V83: =T83-U83 -> 10 | W83: 0 | X83: =V83-W83 -> 10 | Y83: 0 | Z83: =X83-Y83 -> 10 | AA83: 0 | AB83: =Z83-AA83 -> 10 | AC83: 0 | AD83: =AB83-AC83 -> 10 | AE83: 0 | AF83: =AD83-AE83 -> 10 | AG83: 3 | AH83: =AF83-AG83 -> 7 | AI83: 0 | AJ83: =AH83-AI83 -> 7 | AK83: 1 | AL83: =AJ83-AK83 -> 6 | AM83: 2 | AN83: =AL83-AM83 -> 4 | AO83: 0 | AP83: =AN83-AO83 -> 4 | AQ83: 0 | AR83: =AP83-AQ83 -> 4 | AS83: 0 | AT83: =AR83-AS83 -> 4 | AU83: 0 | AV83: =AT83-AU83 -> 4 | AW83: 1 | AX83: =AV83-AW83 -> 3 | AY83: 3 | AZ83: =AX83-AY83 -> 0 | BB83: =AY83+AW83+AU83+AS83+AQ83+AO83+AM83+AK83+AI83+AG83+AE83+AC83+AA83+Y83+W83+U83+S83+Q83+O83+M83+K83 -> 10 | BC83: =$BB83*D83 -> 0 | BD83: =BC83*F83 -> 0 | BE83: =BD83*G83 -> 0 | BF83: =$BB83*E83 -> 0 | BG83: =$BB83*H83 -> 10
B84: 15 | C84: Vue “Plan d’étude” avec liste des tâches du jour. US : En tant qu’étudiant, je vois pour aujourd’hui mes blocs d’étude et tâches, et je peux marquer Done/Not done
C85: Vue quotidienne minimaliste | D85: 0 | E85: 0 | F85: 0 | G85: 0 | H85: 1 | I85: 10 | J85: =I85 -> 10 | K85: 0 | L85: =J85-K85 -> 10 | M85: 0 | N85: =L85-M85 -> 10 | O85: 0 | P85: =N85-O85 -> 10 | Q85: 0 | R85: =P85-Q85 -> 10 | S85: 0 | T85: =R85-S85 -> 10 | U85: 0 | V85: =T85-U85 -> 10 | W85: 0 | X85: =V85-W85 -> 10 | Y85: 0 | Z85: =X85-Y85 -> 10 | AA85: 0 | AB85: =Z85-AA85 -> 10 | AC85: 0 | AD85: =AB85-AC85 -> 10 | AE85: 0 | AF85: =AD85-AE85 -> 10 | AG85: 0 | AH85: =AF85-AG85 -> 10 | AI85: 0 | AJ85: =AH85-AI85 -> 10 | AK85: 2 | AL85: =AJ85-AK85 -> 8 | AM85: 3 | AN85: =AL85-AM85 -> 5 | AO85: 0 | AP85: =AN85-AO85 -> 5 | AR85: =AP85-AQ85 -> 5 | AT85: =AR85-AS85 -> 5 | AV85: =AT85-AU85 -> 5 | AX85: =AV85-AW85 -> 5 | AZ85: =AX85-AY85 -> 5 | BB85: =AY85+AW85+AU85+AS85+AQ85+AO85+AM85+AK85+AI85+AG85+AE85+AC85+AA85+Y85+W85+U85+S85+Q85+O85+M85+K85 -> 5 | BC85: =$BB85*D85 -> 0 | BD85: =BC85*F85 -> 0 | BE85: =BD85*G85 -> 0 | BF85: =$BB85*E85 -> 0 | BG85: =$BB85*H85 -> 5
C86: Toggle Done/Not done | D86: 0 | E86: 0 | F86: 0 | G86: 0 | H86: 1 | I86: 5 | J86: =I86 -> 5 | K86: 0 | L86: =J86-K86 -> 5 | M86: 0 | N86: =L86-M86 -> 5 | O86: 0 | P86: =N86-O86 -> 5 | Q86: 0 | R86: =P86-Q86 -> 5 | S86: 0 | T86: =R86-S86 -> 5 | U86: 0 | V86: =T86-U86 -> 5 | W86: 0 | X86: =V86-W86 -> 5 | Y86: 0 | Z86: =X86-Y86 -> 5 | AA86: 0 | AB86: =Z86-AA86 -> 5 | AC86: 0 | AD86: =AB86-AC86 -> 5 | AE86: 0 | AF86: =AD86-AE86 -> 5 | AG86: 0 | AH86: =AF86-AG86 -> 5 | AI86: 0 | AJ86: =AH86-AI86 -> 5 | AK86: 1 | AL86: =AJ86-AK86 -> 4 | AM86: 2 | AN86: =AL86-AM86 -> 2 | AO86: 0 | AP86: =AN86-AO86 -> 2 | AR86: =AP86-AQ86 -> 2 | AT86: =AR86-AS86 -> 2 | AV86: =AT86-AU86 -> 2 | AX86: =AV86-AW86 -> 2 | AZ86: =AX86-AY86 -> 2 | BB86: =AY86+AW86+AU86+AS86+AQ86+AO86+AM86+AK86+AI86+AG86+AE86+AC86+AA86+Y86+W86+U86+S86+Q86+O86+M86+K86 -> 3 | BC86: =$BB86*D86 -> 0 | BD86: =BC86*F86 -> 0 | BE86: =BD86*G86 -> 0 | BF86: =$BB86*E86 -> 0 | BG86: =$BB86*H86 -> 3
C87: Filtre & état (Tous / À faire / Terminés) | D87: 0 | E87: 0 | F87: 0 | G87: 0 | H87: 1 | I87: 5 | J87: =I87 -> 5 | K87: 0 | L87: =J87-K87 -> 5 | M87: 0 | N87: =L87-M87 -> 5 | O87: 0 | P87: =N87-O87 -> 5 | Q87: 0 | R87: =P87-Q87 -> 5 | S87: 0 | T87: =R87-S87 -> 5 | U87: 0 | V87: =T87-U87 -> 5 | W87: 0 | X87: =V87-W87 -> 5 | Y87: 0 | Z87: =X87-Y87 -> 5 | AA87: 0 | AB87: =Z87-AA87 -> 5 | AC87: 0 | AD87: =AB87-AC87 -> 5 | AE87: 0 | AF87: =AD87-AE87 -> 5 | AG87: 0 | AH87: =AF87-AG87 -> 5 | AI87: 0 | AJ87: =AH87-AI87 -> 5 | AK87: 1 | AL87: =AJ87-AK87 -> 4 | AM87: 1 | AN87: =AL87-AM87 -> 3 | AO87: 0 | AP87: =AN87-AO87 -> 3 | AR87: =AP87-AQ87 -> 3 | AT87: =AR87-AS87 -> 3 | AV87: =AT87-AU87 -> 3 | AX87: =AV87-AW87 -> 3 | AZ87: =AX87-AY87 -> 3 | BB87: =AY87+AW87+AU87+AS87+AQ87+AO87+AM87+AK87+AI87+AG87+AE87+AC87+AA87+Y87+W87+U87+S87+Q87+O87+M87+K87 -> 2 | BC87: =$BB87*D87 -> 0 | BD87: =BC87*F87 -> 0 | BE87: =BD87*G87 -> 0 | BF87: =$BB87*E87 -> 0 | BG87: =$BB87*H87 -> 2
C88: Fonctionnalite chronometre
B89: 16 | C89: Allocation du temps par bloc | D89: 0 | E89: 0 | F89: 0 | G89: 1 | H89: 0 | I89: 10 | J89: =I89 -> 10 | K89: 0 | L89: =J89-K89 -> 10 | M89: 0 | N89: =L89-M89 -> 10 | O89: 0 | P89: =N89-O89 -> 10 | Q89: 0 | R89: =P89-Q89 -> 10 | S89: 3 | T89: =R89-S89 -> 7 | U89: 3 | V89: =T89-U89 -> 4 | W89: 2 | X89: 0 | Y89: 0 | Z89: 0 | AA89: 0 | AB89: =Z89-AA89 -> 0 | AC89: 0 | AD89: =AB89-AC89 -> 0 | AE89: 0 | AF89: =AD89-AE89 -> 0 | AG89: 0 | AH89: =AF89-AG89 -> 0 | AI89: 0 | AJ89: =AH89-AI89 -> 0 | AK89: 0 | AL89: =AJ89-AK89 -> 0 | AM89: 0 | AN89: =AL89-AM89 -> 0 | AO89: 0 | AP89: =AN89-AO89 -> 0 | AQ89: 0 | AR89: =AP89-AQ89 -> 0 | AS89: 0 | AT89: =AR89-AS89 -> 0 | AU89: 0 | AV89: =AT89-AU89 -> 0 | AW89: 0 | AX89: =AV89-AW89 -> 0 | AY89: 0 | AZ89: =AX89-AY89 -> 0 | BB89: =AY89+AW89+AU89+AS89+AQ89+AO89+AM89+AK89+AI89+AG89+AE89+AC89+AA89+Y89+W89+U89+S89+Q89+O89+M89+K89 -> 8 | BC89: =$BB89*D89 -> 0 | BD89: =BC89*F89 -> 0 | BE89: =BD89*G89 -> 0 | BF89: =$BB89*E89 -> 0 | BG89: =$BB89*H89 -> 0
B90: 17 | C90: Fonction pause/reprise | D90: 0 | E90: 0 | F90: 0 | G90: 1 | H90: 0 | I90: 6 | J90: =I90 -> 6 | K90: 0 | L90: =J90-K90 -> 6 | M90: 0 | N90: =L90-M90 -> 6 | O90: 0 | P90: =N90-O90 -> 6 | Q90: 0 | R90: =P90-Q90 -> 6 | S90: 0 | T90: =R90-S90 -> 6 | U90: 0 | V90: 0 | W90: 0 | X90: 6 | Y90: 2 | Z90: =X90-Y90 -> 4 | AA90: 1 | AB90: =Z90-AA90 -> 3 | AC90: 2 | AD90: 0 | AE90: 0 | AF90: =AD90-AE90 -> 0 | AG90: 0 | AH90: =AF90-AG90 -> 0 | AI90: 0 | AJ90: =AH90-AI90 -> 0 | AK90: 0 | AL90: =AJ90-AK90 -> 0 | AM90: 0 | AN90: =AL90-AM90 -> 0 | AO90: 0 | AP90: =AN90-AO90 -> 0 | AQ90: 0 | AR90: =AP90-AQ90 -> 0 | AS90: 0 | AT90: =AR90-AS90 -> 0 | AU90: 0 | AV90: =AT90-AU90 -> 0 | AW90: 0 | AX90: =AV90-AW90 -> 0 | AY90: 0 | AZ90: =AX90-AY90 -> 0 | BB90: =AY90+AW90+AU90+AS90+AQ90+AO90+AM90+AK90+AI90+AG90+AE90+AC90+AA90+Y90+W90+U90+S90+Q90+O90+M90+K90 -> 5 | BC90: =$BB90*D90 -> 0 | BD90: =BC90*F90 -> 0 | BE90: =BD90*G90 -> 0 | BF90: =$BB90*E90 -> 0 | BG90: =$BB90*H90 -> 0
B91: 18 | C91: Arrêt automatique du chronomètre à la fin du bloc | D91: 0 | E91: 0 | F91: 0 | G91: 1 | H91: 0 | I91: 6 | J91: =I91 -> 6 | K91: 0 | L91: =J91-K91 -> 6 | M91: 0 | N91: =L91-M91 -> 6 | O91: 0 | P91: =N91-O91 -> 6 | Q91: 0 | R91: =P91-Q91 -> 6 | S91: 0 | T91: =R91-S91 -> 6 | U91: 0 | V91: 6 | W91: 0 | X91: 6 | Y91: 0 | Z91: =X91-Y91 -> 6 | AA91: 0 | AB91: =Z91-AA91 -> 6 | AC91: 0 | AD91: =AB91-AC91 -> 6 | AE91: 2 | AF91: =AD91-AE91 -> 4 | AG91: 3 | AH91: 0 | AI91: 0 | AJ91: =AH91-AI91 -> 0 | AK91: 0 | AL91: =AJ91-AK91 -> 0 | AM91: 0 | AN91: =AL91-AM91 -> 0 | AO91: 0 | AP91: =AN91-AO91 -> 0 | AQ91: 0 | AR91: =AP91-AQ91 -> 0 | AS91: 0 | AT91: =AR91-AS91 -> 0 | AU91: 0 | AV91: =AT91-AU91 -> 0 | AW91: 0 | AX91: =AV91-AW91 -> 0 | AY91: 0 | AZ91: =AX91-AY91 -> 0 | BB91: =AY91+AW91+AU91+AS91+AQ91+AO91+AM91+AK91+AI91+AG91+AE91+AC91+AA91+Y91+W91+U91+S91+Q91+O91+M91+K91 -> 5 | BC91: =$BB91*D91 -> 0 | BD91: =BC91*F91 -> 0 | BE91: =BD91*G91 -> 0 | BF91: =$BB91*E91 -> 0 | BG91: =$BB91*H91 -> 0
B92: 19 | C92: Gestion de la fin de session avec notification et options pour prolonger la séance | D92: 0 | E92: 0 | F92: 0 | G92: 1 | H92: 0 | I92: 15 | J92: =I92 -> 15 | K92: 0 | L92: =J92-K92 -> 15 | M92: 0 | N92: =L92-M92 -> 15 | O92: 0 | P92: =N92-O92 -> 15 | Q92: 0 | R92: =P92-Q92 -> 15 | S92: 0 | T92: =R92-S92 -> 15 | U92: 0 | V92: =T92-U92 -> 15 | W92: 0 | X92: =V92-W92 -> 15 | Y92: 0 | Z92: =X92-Y92 -> 15 | AA92: 0 | AB92: =Z92-AA92 -> 15 | AC92: 0 | AD92: =AB92-AC92 -> 15 | AE92: 0 | AF92: =AD92-AE92 -> 15 | AG92: 0 | AH92: =AF92-AG92 -> 15 | AI92: 1 | AJ92: =AH92-AI92 -> 14 | AK92: 0 | AL92: =AJ92-AK92 -> 14 | AN92: =AL92-AM92 -> 14 | AP92: =AN92-AO92 -> 14 | AR92: =AP92-AQ92 -> 14 | AT92: =AR92-AS92 -> 14 | AV92: =AT92-AU92 -> 14 | AX92: =AV92-AW92 -> 14 | AZ92: =AX92-AY92 -> 14 | BB92: =AY92+AW92+AU92+AS92+AQ92+AO92+AM92+AK92+AI92+AG92+AE92+AC92+AA92+Y92+W92+U92+S92+Q92+O92+M92+K92 -> 1 | BC92: =$BB92*D92 -> 0 | BD92: =BC92*F92 -> 0 | BE92: =BD92*G92 -> 0 | BF92: =$BB92*E92 -> 0 | BG92: =$BB92*H92 -> 0
B93: 20 | C93: Afficher une vue quotidienne avec la liste des tâches du jour et un bouton “Commencer” pour chaque tâche
C94: Chargement et filtrage des tâches du jour (récupérer les tâches depuis Supabse ou local et filtrer celles dont la date correspond à la journée actuelle) | D94: 0 | E94: 0 | F94: 1 | G94: 0 | H94: 0 | I94: 6 | J94: =I94 -> 6 | L94: =J94-K94 -> 6 | N94: =L94-M94 -> 6 | P94: =N94-O94 -> 6 | R94: =P94-Q94 -> 6 | T94: =R94-S94 -> 6 | V94: =T94-U94 -> 6 | X94: =V94-W94 -> 6 | Z94: =X94-Y94 -> 6 | AB94: =Z94-AA94 -> 6 | AD94: =AB94-AC94 -> 6 | AF94: =AD94-AE94 -> 6 | AH94: =AF94-AG94 -> 6 | AJ94: =AH94-AI94 -> 6 | AL94: =AJ94-AK94 -> 6 | AN94: =AL94-AM94 -> 6 | AP94: =AN94-AO94 -> 6 | AR94: =AP94-AQ94 -> 6 | AT94: =AR94-AS94 -> 6 | AV94: =AT94-AU94 -> 6 | AX94: =AV94-AW94 -> 6 | AZ94: =AX94-AY94 -> 6 | BB94: =AY94+AW94+AU94+AS94+AQ94+AO94+AM94+AK94+AI94+AG94+AE94+AC94+AA94+Y94+W94+U94+S94+Q94+O94+M94+K94 -> 0 | BC94: =$BB94*D94 -> 0 | BD94: =BC94*F94 -> 0 | BE94: =BD94*G94 -> 0 | BF94: =$BB94*E94 -> 0 | BG94: =$BB94*H94 -> 0
C95: Affichage de la vue quotidienne (Créer une interface listant les tâches du jour avec leur titre, catégorie, et statut : "à faire", "en cours", "terminé") | D95: 0 | E95: 0 | F95: 1 | G95: 0 | H95: 0 | I95: 10 | J95: =I95 -> 10 | L95: =J95-K95 -> 10 | N95: =L95-M95 -> 10 | P95: =N95-O95 -> 10 | R95: =P95-Q95 -> 10 | T95: =R95-S95 -> 10 | V95: =T95-U95 -> 10 | X95: =V95-W95 -> 10 | Z95: =X95-Y95 -> 10 | AB95: =Z95-AA95 -> 10 | AD95: =AB95-AC95 -> 10 | AF95: =AD95-AE95 -> 10 | AH95: =AF95-AG95 -> 10 | AJ95: =AH95-AI95 -> 10 | AL95: =AJ95-AK95 -> 10 | AN95: =AL95-AM95 -> 10 | AP95: =AN95-AO95 -> 10 | AR95: =AP95-AQ95 -> 10 | AT95: =AR95-AS95 -> 10 | AV95: =AT95-AU95 -> 10 | AX95: =AV95-AW95 -> 10 | AZ95: =AX95-AY95 -> 10 | BB95: =AY95+AW95+AU95+AS95+AQ95+AO95+AM95+AK95+AI95+AG95+AE95+AC95+AA95+Y95+W95+U95+S95+Q95+O95+M95+K95 -> 0 | BC95: =$BB95*D95 -> 0 | BD95: =BC95*F95 -> 0 | BE95: =BD95*G95 -> 0 | BF95: =$BB95*E95 -> 0 | BG95: =$BB95*H95 -> 0
C96: Ajout du bouton "Commencer". (pour chaque tâche, ajouter un bouton "commencer" qui met à jour l'état de la tâche et affiche un retour visuel) | D96: 0 | E96: 0 | F96: 1 | G96: 0 | H96: 0 | I96: 6 | J96: =I96 -> 6 | L96: =J96-K96 -> 6 | N96: =L96-M96 -> 6 | P96: =N96-O96 -> 6 | R96: =P96-Q96 -> 6 | T96: =R96-S96 -> 6 | V96: =T96-U96 -> 6 | X96: =V96-W96 -> 6 | Z96: =X96-Y96 -> 6 | AB96: =Z96-AA96 -> 6 | AD96: =AB96-AC96 -> 6 | AF96: =AD96-AE96 -> 6 | AH96: =AF96-AG96 -> 6 | AJ96: =AH96-AI96 -> 6 | AL96: =AJ96-AK96 -> 6 | AN96: =AL96-AM96 -> 6 | AP96: =AN96-AO96 -> 6 | AR96: =AP96-AQ96 -> 6 | AT96: =AR96-AS96 -> 6 | AV96: =AT96-AU96 -> 6 | AX96: =AV96-AW96 -> 6 | AZ96: =AX96-AY96 -> 6 | BB96: =AY96+AW96+AU96+AS96+AQ96+AO96+AM96+AK96+AI96+AG96+AE96+AC96+AA96+Y96+W96+U96+S96+Q96+O96+M96+K96 -> 0 | BC96: =$BB96*D96 -> 0 | BD96: =BC96*F96 -> 0 | BE96: =BD96*G96 -> 0 | BF96: =$BB96*E96 -> 0 | BG96: =$BB96*H96 -> 0
B97: 21 | C97: Gestion des revenus et dépenses
C98: Précision issue : Ajouter des revenus | D98: 0 | E98: 1 | F98: 0 | G98: 0 | H98: 0 | I98: 10 | J98: =I98 -> 10 | K98: 0 | L98: =J98-K98 -> 10 | M98: 0 | N98: =L98-M98 -> 10 | O98: 0 | P98: =N98-O98 -> 10 | Q98: 0 | R98: =P98-Q98 -> 10 | S98: 0 | T98: =R98-S98 -> 10 | U98: 0 | V98: =T98-U98 -> 10 | W98: 0 | X98: =V98-W98 -> 10 | Y98: 0 | Z98: =X98-Y98 -> 10 | AA98: 0 | AB98: =Z98-AA98 -> 10 | AC98: 0 | AD98: =AB98-AC98 -> 10 | AE98: 0 | AF98: =AD98-AE98 -> 10 | AG98: 3 | AH98: =AF98-AG98 -> 7 | AI98: 4 | AJ98: 3 | AK98: 2 | AL98: 0 | AN98: =AL98-AM98 -> 0 | AP98: =AN98-AO98 -> 0 | AR98: =AP98-AQ98 -> 0 | AT98: =AR98-AS98 -> 0 | AV98: =AT98-AU98 -> 0 | AX98: =AV98-AW98 -> 0 | AZ98: =AX98-AY98 -> 0 | BB98: =AY98+AW98+AU98+AS98+AQ98+AO98+AM98+AK98+AI98+AG98+AE98+AC98+AA98+Y98+W98+U98+S98+Q98+O98+M98+K98 -> 9 | BC98: =$BB98*D98 -> 0 | BD98: =BC98*F98 -> 0 | BE98: =BD98*G98 -> 0 | BF98: =$BB98*E98 -> 9 | BG98: =$BB98*H98 -> 0
B99: 22 | C99: Gestion des revenus et dépenses
C100: Précision issue : Modifier revenus (éditer ou supprimer) | D100: 0 | E100: 1 | F100: 0 | G100: 0 | H100: 0 | I100: 8 | J100: =I100 -> 8 | K100: 0 | L100: =J100-K100 -> 8 | M100: 0 | N100: =L100-M100 -> 8 | O100: 0 | P100: =N100-O100 -> 8 | Q100: 0 | R100: =P100-Q100 -> 8 | S100: 0 | T100: =R100-S100 -> 8 | U100: 0 | V100: =T100-U100 -> 8 | W100: 0 | X100: =V100-W100 -> 8 | Y100: 0 | Z100: =X100-Y100 -> 8 | AA100: 0 | AB100: =Z100-AA100 -> 8 | AC100: 0 | AD100: =AB100-AC100 -> 8 | AE100: 0 | AF100: =AD100-AE100 -> 8 | AG100: 2 | AH100: =AF100-AG100 -> 6 | AI100: 2 | AJ100: =AH100-AI100 -> 4 | AK100: 1 | AL100: 0 | AN100: =AL100-AM100 -> 0 | AP100: =AN100-AO100 -> 0 | AR100: =AP100-AQ100 -> 0 | AT100: =AR100-AS100 -> 0 | AV100: =AT100-AU100 -> 0 | AX100: =AV100-AW100 -> 0 | AZ100: =AX100-AY100 -> 0 | BB100: =AY100+AW100+AU100+AS100+AQ100+AO100+AM100+AK100+AI100+AG100+AE100+AC100+AA100+Y100+W100+U100+S100+Q100+O100+M100+K100 -> 5 | BC100: =$BB100*D100 -> 0 | BD100: =BC100*F100 -> 0 | BE100: =BD100*G100 -> 0 | BF100: =$BB100*E100 -> 5 | BG100: =$BB100*H100 -> 0
B101: 23 | C101: Gestion des revenus et dépenses
C102: Ajouter les dépenses par rapport aux études (coût trimestre, etc.) | D102: 0 | E102: 1 | F102: 0 | G102: 0 | H102: 0 | I102: 8 | J102: =I102 -> 8 | K102: 0 | L102: =J102-K102 -> 8 | M102: 0 | N102: =L102-M102 -> 8 | O102: 0 | P102: =N102-O102 -> 8 | Q102: 0 | R102: =P102-Q102 -> 8 | S102: 0 | T102: =R102-S102 -> 8 | U102: 0 | V102: =T102-U102 -> 8 | W102: 0 | X102: =V102-W102 -> 8 | Y102: 0 | Z102: 8 | AA102: 0 | AB102: =Z102-AA102 -> 8 | AC102: 0 | AD102: =AB102-AC102 -> 8 | AE102: 0 | AF102: =AD102-AE102 -> 8 | AG102: 3 | AH102: =AF102-AG102 -> 5 | AI102: 2 | AJ102: 1 | AK102: 1 | AL102: =AJ102-AK102 -> 0 | AN102: =AL102-AM102 -> 0 | AP102: =AN102-AO102 -> 0 | AR102: =AP102-AQ102 -> 0 | AT102: =AR102-AS102 -> 0 | AV102: =AT102-AU102 -> 0 | AX102: =AV102-AW102 -> 0 | AZ102: =AX102-AY102 -> 0 | BB102: =AY102+AW102+AU102+AS102+AQ102+AO102+AM102+AK102+AI102+AG102+AE102+AC102+AA102+Y102+W102+U102+S102+Q102+O102+M102+K102 -> 6 | BC102: =$BB102*D102 -> 0 | BD102: =BC102*F102 -> 0 | BE102: =BD102*G102 -> 0 | BF102: =$BB102*E102 -> 6 | BG102: =$BB102*H102 -> 0
...

Sheet team
A1: Prénom | B1: Nom | C1: email | D1: nickname
A2: Oryna | B2: Kubarieva | C2: kubarieva.oryna@courrier.uqam.ca | D2: =A2 -> Oryna
A3: Aziz | B3: Thiam | C3: thiam.demba_aziz@courrier.uqam.ca | D3: =A3 -> Aziz
A4: Joana | B4: Munyaneza | C4: munyaneza_mutunge.ursule_joana@courrier.uqam.ca | D4: =A4 -> Joana
A5: Kenny | B5: Kenfack | C5: kenfack_nandjou.steve_marvyn@courrier.uqam.ca | D5: =A5 -> Kenny
A6: Romuald | B6: Sokoujou | C6: kenfack_nandjou.steve_marvyn@courrier.uqam.ca | D6: =A6 -> Romuald
